<response><header><resultCode>000</resultCode><resultMsg>OK</resultMsg></header><body><items><item><aptDong> </aptDong><aptNm>프라임펠리스</aptNm><buildYear>2012</buildYear><buyerGbn> </buyerGbn><cdealDay>23.02.01</cdealDay><cdealType>O</cdealType><dealAmount>15,500</dealAmount><dealDay>25</dealDay><dealMonth>11</dealMonth><dealYear>2022</dealYear><dealingGbn>중개거래</dealingGbn><estateAgentSggNm>서울 용산구</estateAgentSggNm><excluUseAr>13.69</excluUseAr><floor>17</floor><jibun>24-8</jibun><landLeaseholdGbn>N</landLeaseholdGbn><rgstDate> </rgstDate><sggCd>11170</sggCd><slerGbn> </slerGbn><umdNm>문배동</umdNm></item><item><aptDong> </aptDong><aptNm>주미</aptNm><buildYear>1973</buildYear><buyerGbn> </buyerGbn><cdealDay> </cdealDay><cdealType> </cdealType><dealAmount>143,000</dealAmount><dealDay>29</dealDay><dealMonth>11</dealMonth><dealYear>2022</dealYear><dealingGbn>중개거래</dealingGbn><estateAgentSggNm>서울 용산구</estateAgentSggNm><excluUseAr>69.39</excluUseAr><floor>9</floor><jibun>260-6</jibun><landLeaseholdGbn>N</landLeaseholdGbn><rgstDate> </rgstDate><sggCd>11170</sggCd><slerGbn> </slerGbn><umdNm>보광동</umdNm></item><item><aptDong> </aptDong><aptNm>용암한신</aptNm><buildYear>1982</buildYear><buyerGbn> </buyerGbn><cdealDay> </cdealDay><cdealType> </cdealType><dealAmount>60,000</dealAmount><dealDay>24</dealDay><dealMonth>11</dealMonth><dealYear>2022</dealYear><dealingGbn>중개거래</dealingGbn><estateAgentSggNm>서울 중구</estateAgentSggNm><excluUseAr>72.66</excluUseAr><floor>5</floor><jibun>47-5</jibun><landLeaseholdGbn>N</landLeaseholdGbn><rgstDate> </rgstDate><sggCd>11170</sggCd><slerGbn> </slerGbn><umdNm>용산동2가</umdNm></item><item><aptDong> </aptDong><aptNm>장미1</aptNm><buildYear>1976</buildYear><buyerGbn> </buyerGbn><cdealDay> </cdealDay><cdealType> </cdealType><dealAmount>176,000</dealAmount><dealDay>17</dealDay><dealMonth>11</dealMonth><dealYear>2022</dealYear><dealingGbn>중개거래</dealingGbn><estateAgentSggNm>서울 용산구</estateAgentSggNm><excluUseAr>74.38</excluUseAr><floor>3</floor><jibun>732-19</jibun><landLeaseholdGbn>N</landLeaseholdGbn><rgstDate> </rgstDate><sggCd>11170</sggCd><slerGbn> </slerGbn><umdNm>한남동</umdNm></item><item><aptDong> </aptDong><aptNm>이촌동삼성리버스위트</aptNm><buildYear>2002</buildYear><buyerGbn> </buyerGbn><cdealDay> </cdealDay><cdealType> </cdealType><dealAmount>375,000</dealAmount><dealDay>23</dealDay><dealMonth>11</dealMonth><dealYear>2022</dealYear><dealingGbn>중개거래</dealingGbn><estateAgentSggNm>서울 용산구</estateAgentSggNm><excluUseAr>180.82</excluUseAr><floor>5</floor><jibun>426</jibun><landLeaseholdGbn>N</landLeaseholdGbn><rgstDate> </rgstDate><sggCd>11170</sggCd><slerGbn> </slerGbn><umdNm>이촌동</umdNm></item><item><aptDong> </aptDong><aptNm>한강로대우아이빌</aptNm><buildYear>2004</buildYear><buyerGbn> </buyerGbn><cdealDay> </cdealDay><cdealType> </cdealType><dealAmount>36,500</dealAmount><dealDay>27</dealDay><dealMonth>11</dealMonth><dealYear>2022</dealYear><dealingGbn>중개거래</dealingGbn><estateAgentSggNm>서울 강남구 서울 용산구</estateAgentSggNm><excluUseAr>28.22</excluUseAr><floor>15</floor><jibun>2-11</jibun><landLeaseholdGbn>N</landLeaseholdGbn><rgstDate> </rgstDate><sggCd>11170</sggCd><slerGbn> </slerGbn><umdNm>한강로2가</umdNm></item><item><aptDong> </aptDong><aptNm>나인원한남</aptNm><buildYear>2019</buildYear><buyerGbn> </buyerGbn><cdealDay> </cdealDay><cdealType> </cdealType><dealAmount>945,000</dealAmount><dealDay>7</dealDay><dealMonth>11</dealMonth><dealYear>2022</dealYear><dealingGbn>중개거래</dealingGbn><estateAgentSggNm>서울 용산구</estateAgentSggNm><excluUseAr>206.8953</excluUseAr><floor>8</floor><jibun>829</jibun><landLeaseholdGbn>N</landLeaseholdGbn><rgstDate> </rgstDate><sggCd>11170</sggCd><slerGbn> </slerGbn><umdNm>한남동</umdNm></item><item><aptDong> </aptDong><aptNm>장미1</aptNm><buildYear>1976</buildYear><buyerGbn> </buyerGbn><cdealDay>22.12.08</cdealDay><cdealType>O</cdealType><dealAmount>176,000</dealAmount><dealDay>17</dealDay><dealMonth>11</dealMonth><dealYear>2022</dealYear><dealingGbn>중개거래</dealingGbn><estateAgentSggNm>서울 용산구</estateAgentSggNm><excluUseAr>74.38</excluUseAr><floor>3</floor><jibun>732-19</jibun><landLeaseholdGbn>N</landLeaseholdGbn><rgstDate> </rgstDate><sggCd>11170</sggCd><slerGbn> </slerGbn><umdNm>한남동</umdNm></item><item><aptDong> </aptDong><aptNm>주미</aptNm><buildYear>1973</buildYear><buyerGbn> </buyerGbn><cdealDay> </cdealDay><cdealType> </cdealType><dealAmount>149,150</dealAmount><dealDay>5</dealDay><dealMonth>11</dealMonth><dealYear>2022</dealYear><dealingGbn>중개거래</dealingGbn><estateAgentSggNm>서울 용산구</estateAgentSggNm><excluUseAr>79.21</excluUseAr><floor>7</floor><jibun>260-6</jibun><landLeaseholdGbn>N</landLeaseholdGbn><rgstDate> </rgstDate><sggCd>11170</sggCd><slerGbn> </slerGbn><umdNm>보광동</umdNm></item><item><aptDong> </aptDong><aptNm>이촌코오롱(A)</aptNm><buildYear>1999</buildYear><buyerGbn> </buyerGbn><cdealDay> </cdealDay><cdealType> </cdealType><dealAmount>200,000</dealAmount><dealDay>18</dealDay><dealMonth>11</dealMonth><dealYear>2022</dealYear><dealingGbn>중개거래</dealingGbn><estateAgentSggNm>서울 용산구</estateAgentSggNm><excluUseAr>114.69</excluUseAr><floor>6</floor><jibun>412</jibun><landLeaseholdGbn>N</landLeaseholdGbn><rgstDate> </rgstDate><sggCd>11170</sggCd><slerGbn> </slerGbn><umdNm>이촌동</umdNm></item><item><aptDong> </aptDong><aptNm>센트럴파크</aptNm><buildYear>2020</buildYear><buyerGbn> </buyerGbn><cdealDay> </cdealDay><cdealType> </cdealType><dealAmount>290,000</dealAmount><dealDay>7</dealDay><dealMonth>11</dealMonth><dealYear>2022</dealYear><dealingGbn>중개거래</dealingGbn><estateAgentSggNm>서울 용산구</estateAgentSggNm><excluUseAr>102.8617</excluUseAr><floor>27</floor><jibun>98</jibun><landLeaseholdGbn>N</landLeaseholdGbn><rgstDate> </rgstDate><sggCd>11170</sggCd><slerGbn> </slerGbn><umdNm>한강로3가</umdNm></item><item><aptDong> </aptDong><aptNm>동아그린</aptNm><buildYear>1999</buildYear><buyerGbn> </buyerGbn><cdealDay> </cdealDay><cdealType> </cdealType><dealAmount>99,000</dealAmount><dealDay>8</dealDay><dealMonth>11</dealMonth><dealYear>2022</dealYear><dealingGbn>중개거래</dealingGbn><estateAgentSggNm>서울 용산구</estateAgentSggNm><excluUseAr>43.02</excluUseAr><floor>12</floor><jibun>411</jibun><landLeaseholdGbn>N</landLeaseholdGbn><rgstDate> </rgstDate><sggCd>11170</sggCd><slerGbn> </slerGbn><umdNm>이촌동</umdNm></item><item><aptDong> </aptDong><aptNm>장미1</aptNm><buildYear>1976</buildYear><buyerGbn> </buyerGbn><cdealDay> </cdealDay><cdealType> </cdealType><dealAmount>169,000</dealAmount><dealDay>8</dealDay><dealMonth>11</dealMonth><dealYear>2022</dealYear><dealingGbn>중개거래</dealingGbn><estateAgentSggNm>서울 용산구</estateAgentSggNm><excluUseAr>77.39</excluUseAr><floor>1</floor><jibun>732-19</jibun><landLeaseholdGbn>N</landLeaseholdGbn><rgstDate> </rgstDate><sggCd>11170</sggCd><slerGbn> </slerGbn><umdNm>한남동</umdNm></item><item><aptDong> </aptDong><aptNm>프라임펠리스</aptNm><buildYear>2012</buildYear><buyerGbn> </buyerGbn><cdealDay> </cdealDay><cdealType> </cdealType><dealAmount>16,500</dealAmount><dealDay>15</dealDay><dealMonth>11</dealMonth><dealYear>2022</dealYear><dealingGbn>중개거래</dealingGbn><estateAgentSggNm>서울 용산구</estateAgentSggNm><excluUseAr>13.69</excluUseAr><floor>18</floor><jibun>24-8</jibun><landLeaseholdGbn>N</landLeaseholdGbn><rgstDate> </rgstDate><sggCd>11170</sggCd><slerGbn> </slerGbn><umdNm>문배동</umdNm></item><item><aptDong> </aptDong><aptNm>프라임펠리스</aptNm><buildYear>2012</buildYear><buyerGbn> </buyerGbn><cdealDay> </cdealDay><cdealType> </cdealType><dealAmount>16,500</dealAmount><dealDay>19</dealDay><dealMonth>11</dealMonth><dealYear>2022</dealYear><dealingGbn>중개거래</dealingGbn><estateAgentSggNm>서울 용산구</estateAgentSggNm><excluUseAr>13.69</excluUseAr><floor>14</floor><jibun>24-8</jibun><landLeaseholdGbn>N</landLeaseholdGbn><rgstDate> </rgstDate><sggCd>11170</sggCd><slerGbn> </slerGbn><umdNm>문배동</umdNm></item><item><aptDong> </aptDong><aptNm>용산파크자이</aptNm><buildYear>2005</buildYear><buyerGbn> </buyerGbn><cdealDay> </cdealDay><cdealType> </cdealType><dealAmount>160,000</dealAmount><dealDay>7</dealDay><dealMonth>11</dealMonth><dealYear>2022</dealYear><dealingGbn>중개거래</dealingGbn><estateAgentSggNm>서울 강남구</estateAgentSggNm><excluUseAr>99.85</excluUseAr><floor>6</floor><jibun>50-1</jibun><landLeaseholdGbn>N</landLeaseholdGbn><rgstDate> </rgstDate><sggCd>11170</sggCd><slerGbn> </slerGbn><umdNm>한강로1가</umdNm></item></items><numOfRows>100</numOfRows><pageNo>1</pageNo><totalCount>16</totalCount></body></response>