<response><header><resultCode>000</resultCode><resultMsg>OK</resultMsg></header><body><items><item><aptDong>811</aptDong><aptNm>길음뉴타운8단지(래미안)</aptNm><buildYear>2010</buildYear><buyerGbn>개인</buyerGbn><cdealDay> </cdealDay><cdealType> </cdealType><dealAmount>83,500</dealAmount><dealDay>2</dealDay><dealMonth>1</dealMonth><dealYear>2024</dealYear><dealingGbn>중개거래</dealingGbn><estateAgentSggNm>경기 군포시, 서울 성북구</estateAgentSggNm><excluUseAr>59.99</excluUseAr><floor>20</floor><jibun>1284</jibun><landLeaseholdGbn>N</landLeaseholdGbn><rgstDate>24.04.15</rgstDate><sggCd>11290</sggCd><slerGbn>개인</slerGbn><umdNm>길음동</umdNm></item><item><aptDong>107</aptDong><aptNm>정릉e-편한세상</aptNm><buildYear>2006</buildYear><buyerGbn>개인</buyerGbn><cdealDay> </cdealDay><cdealType> </cdealType><dealAmount>59,500</dealAmount><dealDay>30</dealDay><dealMonth>1</dealMonth><dealYear>2024</dealYear><dealingGbn>중개거래</dealingGbn><estateAgentSggNm>서울 성북구</estateAgentSggNm><excluUseAr>59.77</excluUseAr><floor>19</floor><jibun>1028</jibun><landLeaseholdGbn>N</landLeaseholdGbn><rgstDate>24.03.25</rgstDate><sggCd>11290</sggCd><slerGbn>개인</slerGbn><umdNm>정릉동</umdNm></item><item><aptDong>108</aptDong><aptNm>길음뉴타운경남아너스빌</aptNm><buildYear>1999</buildYear><buyerGbn>개인</buyerGbn><cdealDay> </cdealDay><cdealType> </cdealType><dealAmount>52,000</dealAmount><dealDay>29</dealDay><dealMonth>1</dealMonth><dealYear>2024</dealYear><dealingGbn>중개거래</dealingGbn><estateAgentSggNm>경기 김포시, 서울 성북구</estateAgentSggNm><excluUseAr>50.45</excluUseAr><floor>12</floor><jibun>1015</jibun><landLeaseholdGbn>N</landLeaseholdGbn><rgstDate>24.04.09</rgstDate><sggCd>11290</sggCd><slerGbn>개인</slerGbn><umdNm>정릉동</umdNm></item><item><aptDong> </aptDong><aptNm>코아루센타시아</aptNm><buildYear>2010</buildYear><buyerGbn>개인</buyerGbn><cdealDay> </cdealDay><cdealType> </cdealType><dealAmount>84,500</dealAmount><dealDay>30</dealDay><dealMonth>1</dealMonth><dealYear>2024</dealYear><dealingGbn>중개거래</dealingGbn><estateAgentSggNm>서울 성북구</estateAgentSggNm><excluUseAr>113.02</excluUseAr><floor>8</floor><jibun>121-6</jibun><landLeaseholdGbn>N</landLeaseholdGbn><rgstDate>24.04.08</rgstDate><sggCd>11290</sggCd><slerGbn>개인</slerGbn><umdNm>동선동1가</umdNm></item><item><aptDong>103</aptDong><aptNm>정릉e-편한세상</aptNm><buildYear>2006</buildYear><buyerGbn>개인</buyerGbn><cdealDay> </cdealDay><cdealType> </cdealType><dealAmount>66,500</dealAmount><dealDay>31</dealDay><dealMonth>1</dealMonth><dealYear>2024</dealYear><dealingGbn>중개거래</dealingGbn><estateAgentSggNm>서울 성북구</estateAgentSggNm><excluUseAr>85</excluUseAr><floor>2</floor><jibun>1028</jibun><landLeaseholdGbn>N</landLeaseholdGbn><rgstDate>24.05.20</rgstDate><sggCd>11290</sggCd><slerGbn>개인</slerGbn><umdNm>정릉동</umdNm></item><item><aptDong>113</aptDong><aptNm>롯데캐슬클라시아</aptNm><buildYear>2022</buildYear><buyerGbn>개인</buyerGbn><cdealDay> </cdealDay><cdealType> </cdealType><dealAmount>99,000</dealAmount><dealDay>27</dealDay><dealMonth>1</dealMonth><dealYear>2024</dealYear><dealingGbn>중개거래</dealingGbn><estateAgentSggNm>서울 성북구</estateAgentSggNm><excluUseAr>59.8826</excluUseAr><floor>5</floor><jibun>1289</jibun><landLeaseholdGbn>N</landLeaseholdGbn><rgstDate>24.05.10</rgstDate><sggCd>11290</sggCd><slerGbn>개인</slerGbn><umdNm>길음동</umdNm></item><item><aptDong>110</aptDong><aptNm>석관래미안</aptNm><buildYear>2009</buildYear><buyerGbn>개인</buyerGbn><cdealDay> </cdealDay><cdealType> </cdealType><dealAmount>74,900</dealAmount><dealDay>26</dealDay><dealMonth>1</dealMonth><dealYear>2024</dealYear><dealingGbn>중개거래</dealingGbn><estateAgentSggNm>경기 의정부시, 서울 성북구</estateAgentSggNm><excluUseAr>59.9</excluUseAr><floor>6</floor><jibun>407</jibun><landLeaseholdGbn>N</landLeaseholdGbn><rgstDate>24.04.19</rgstDate><sggCd>11290</sggCd><slerGbn>개인</slerGbn><umdNm>석관동</umdNm></item><item><aptDong>102</aptDong><aptNm>한신</aptNm><buildYear>1998</buildYear><buyerGbn>개인</buyerGbn><cdealDay> </cdealDay><cdealType> </cdealType><dealAmount>85,000</dealAmount><dealDay>31</dealDay><dealMonth>1</dealMonth><dealYear>2024</dealYear><dealingGbn>중개거래</dealingGbn><estateAgentSggNm>서울 성북구</estateAgentSggNm><excluUseAr>84.87</excluUseAr><floor>12</floor><jibun>609-1</jibun><landLeaseholdGbn>N</landLeaseholdGbn><rgstDate>24.06.14</rgstDate><sggCd>11290</sggCd><slerGbn>개인</slerGbn><umdNm>돈암동</umdNm></item><item><aptDong>105</aptDong><aptNm>돈암동삼성</aptNm><buildYear>1999</buildYear><buyerGbn>개인</buyerGbn><cdealDay> </cdealDay><cdealType> </cdealType><dealAmount>72,150</dealAmount><dealDay>9</dealDay><dealMonth>1</dealMonth><dealYear>2024</dealYear><dealingGbn>중개거래</dealingGbn><estateAgentSggNm>서울 성북구</estateAgentSggNm><excluUseAr>84.59</excluUseAr><floor>7</floor><jibun>15-1</jibun><landLeaseholdGbn>N</landLeaseholdGbn><rgstDate>24.03.27</rgstDate><sggCd>11290</sggCd><slerGbn>개인</slerGbn><umdNm>돈암동</umdNm></item><item><aptDong>108</aptDong><aptNm>한신</aptNm><buildYear>1998</buildYear><buyerGbn>개인</buyerGbn><cdealDay> </cdealDay><cdealType> </cdealType><dealAmount>90,000</dealAmount><dealDay>21</dealDay><dealMonth>1</dealMonth><dealYear>2024</dealYear><dealingGbn>중개거래</dealingGbn><estateAgentSggNm>서울 성북구</estateAgentSggNm><excluUseAr>132.96</excluUseAr><floor>8</floor><jibun>609-1</jibun><landLeaseholdGbn>N</landLeaseholdGbn><rgstDate>24.04.19</rgstDate><sggCd>11290</sggCd><slerGbn>개인</slerGbn><umdNm>돈암동</umdNm></item><item><aptDong>126</aptDong><aptNm>래미안월곡</aptNm><buildYear>2006</buildYear><buyerGbn>개인</buyerGbn><cdealDay> </cdealDay><cdealType> </cdealType><dealAmount>71,000</dealAmount><dealDay>26</dealDay><dealMonth>1</dealMonth><dealYear>2024</dealYear><dealingGbn>중개거래</dealingGbn><estateAgentSggNm>서울 성북구</estateAgentSggNm><excluUseAr>59.754</excluUseAr><floor>6</floor><jibun>225</jibun><landLeaseholdGbn>N</landLeaseholdGbn><rgstDate>24.06.13</rgstDate><sggCd>11290</sggCd><slerGbn>개인</slerGbn><umdNm>하월곡동</umdNm></item><item><aptDong>506</aptDong><aptNm>래미안장위퍼스트하이</aptNm><buildYear>2020</buildYear><buyerGbn>개인</buyerGbn><cdealDay> </cdealDay><cdealType> </cdealType><dealAmount>81,500</dealAmount><dealDay>25</dealDay><dealMonth>1</dealMonth><dealYear>2024</dealYear><dealingGbn>중개거래</dealingGbn><estateAgentSggNm>서울 성북구</estateAgentSggNm><excluUseAr>59.99</excluUseAr><floor>23</floor><jibun>320</jibun><landLeaseholdGbn>N</landLeaseholdGbn><rgstDate>24.03.29</rgstDate><sggCd>11290</sggCd><slerGbn>개인</slerGbn><umdNm>장위동</umdNm></item><item><aptDong>114</aptDong><aptNm>월곡두산위브</aptNm><buildYear>2003</buildYear><buyerGbn>개인</buyerGbn><cdealDay> </cdealDay><cdealType> </cdealType><dealAmount>66,000</dealAmount><dealDay>27</dealDay><dealMonth>1</dealMonth><dealYear>2024</dealYear><dealingGbn>중개거래</dealingGbn><estateAgentSggNm>서울 성북구</estateAgentSggNm><excluUseAr>59.855</excluUseAr><floor>13</floor><jibun>222</jibun><landLeaseholdGbn>N</landLeaseholdGbn><rgstDate>24.03.20</rgstDate><sggCd>11290</sggCd><slerGbn>개인</slerGbn><umdNm>하월곡동</umdNm></item><item><aptDong>104</aptDong><aptNm>한신</aptNm><buildYear>1998</buildYear><buyerGbn>개인</buyerGbn><cdealDay> </cdealDay><cdealType> </cdealType><dealAmount>103,000</dealAmount><dealDay>20</dealDay><dealMonth>1</dealMonth><dealYear>2024</dealYear><dealingGbn>중개거래</dealingGbn><estateAgentSggNm>서울 성북구</estateAgentSggNm><excluUseAr>132.96</excluUseAr><floor>3</floor><jibun>609-1</jibun><landLeaseholdGbn>N</landLeaseholdGbn><rgstDate>24.04.26</rgstDate><sggCd>11290</sggCd><slerGbn>개인</slerGbn><umdNm>돈암동</umdNm></item><item><aptDong> </aptDong><aptNm>정릉e-편한세상</aptNm><buildYear>2006</buildYear><buyerGbn>개인</buyerGbn><cdealDay>24.03.19</cdealDay><cdealType>O</cdealType><dealAmount>59,500</dealAmount><dealDay>30</dealDay><dealMonth>1</dealMonth><dealYear>2024</dealYear><dealingGbn>중개거래</dealingGbn><estateAgentSggNm>서울 성북구</estateAgentSggNm><excluUseAr>59.77</excluUseAr><floor>19</floor><jibun>1028</jibun><landLeaseholdGbn>N</landLeaseholdGbn><rgstDate> </rgstDate><sggCd>11290</sggCd><slerGbn>개인</slerGbn><umdNm>정릉동</umdNm></item><item><aptDong>104</aptDong><aptNm>동일하이빌뉴시티</aptNm><buildYear>2011</buildYear><buyerGbn>개인</buyerGbn><cdealDay> </cdealDay><cdealType> </cdealType><dealAmount>131,000</dealAmount><dealDay>30</dealDay><dealMonth>1</dealMonth><dealYear>2024</dealYear><dealingGbn>중개거래</dealingGbn><estateAgentSggNm>서울 성북구</estateAgentSggNm><excluUseAr>133.74</excluUseAr><floor>25</floor><jibun>230</jibun><landLeaseholdGbn>N</landLeaseholdGbn><rgstDate>24.02.29</rgstDate><sggCd>11290</sggCd><slerGbn>개인</slerGbn><umdNm>하월곡동</umdNm></item><item><aptDong>104</aptDong><aptNm>래미안포레카운티</aptNm><buildYear>2021</buildYear><buyerGbn>개인</buyerGbn><cdealDay> </cdealDay><cdealType> </cdealType><dealAmount>83,000</dealAmount><dealDay>30</dealDay><dealMonth>1</dealMonth><dealYear>2024</dealYear><dealingGbn>중개거래</dealingGbn><estateAgentSggNm>서울 성북구</estateAgentSggNm><excluUseAr>59.92</excluUseAr><floor>5</floor><jibun>322</jibun><landLeaseholdGbn>N</landLeaseholdGbn><rgstDate>24.06.07</rgstDate><sggCd>11290</sggCd><slerGbn>개인</slerGbn><umdNm>장위동</umdNm></item><item><aptDong> </aptDong><aptNm>구현대</aptNm><buildYear>1981</buildYear><buyerGbn>기타</buyerGbn><cdealDay> </cdealDay><cdealType> </cdealType><dealAmount>61,300</dealAmount><dealDay>15</dealDay><dealMonth>1</dealMonth><dealYear>2024</dealYear><dealingGbn>직거래</dealingGbn><estateAgentSggNm> </estateAgentSggNm><excluUseAr>51.47</excluUseAr><floor>2</floor><jibun>624</jibun><landLeaseholdGbn>N</landLeaseholdGbn><rgstDate> </rgstDate><sggCd>11290</sggCd><slerGbn>개인</slerGbn><umdNm>돈암동</umdNm></item><item><aptDong>107</aptDong><aptNm>정릉e-편한세상</aptNm><buildYear>2006</buildYear><buyerGbn>개인</buyerGbn><cdealDay> </cdealDay><cdealType> </cdealType><dealAmount>57,000</dealAmount><dealDay>24</dealDay><dealMonth>1</dealMonth><dealYear>2024</dealYear><dealingGbn>중개거래</dealingGbn><estateAgentSggNm>서울 성북구</estateAgentSggNm><excluUseAr>59.77</excluUseAr><floor>8</floor><jibun>1028</jibun><landLeaseholdGbn>N</landLeaseholdGbn><rgstDate>24.03.28</rgstDate><sggCd>11290</sggCd><slerGbn>개인</slerGbn><umdNm>정릉동</umdNm></item><item><aptDong>503</aptDong><aptNm>래미안장위퍼스트하이</aptNm><buildYear>2020</buildYear><buyerGbn>개인</buyerGbn><cdealDay> </cdealDay><cdealType> </cdealType><dealAmount>98,500</dealAmount><dealDay>27</dealDay><dealMonth>1</dealMonth><dealYear>2024</dealYear><dealingGbn>중개거래</dealingGbn><estateAgentSggNm>서울 성북구</estateAgentSggNm><excluUseAr>84.94</excluUseAr><floor>18</floor><jibun>320</jibun><landLeaseholdGbn>N</landLeaseholdGbn><rgstDate>24.04.11</rgstDate><sggCd>11290</sggCd><slerGbn>개인</slerGbn><umdNm>장위동</umdNm></item><item><aptDong>104</aptDong><aptNm>종암에스케이</aptNm><buildYear>1999</buildYear><buyerGbn>개인</buyerGbn><cdealDay> </cdealDay><cdealType> </cdealType><dealAmount>72,000</dealAmount><dealDay>22</dealDay><dealMonth>1</dealMonth><dealYear>2024</dealYear><dealingGbn>중개거래</dealingGbn><estateAgentSggNm>서울 성북구</estateAgentSggNm><excluUseAr>84.72</excluUseAr><floor>17</floor><jibun>104-1</jibun><landLeaseholdGbn>N</landLeaseholdGbn><rgstDate>24.03.14</rgstDate><sggCd>11290</sggCd><slerGbn>개인</slerGbn><umdNm>종암동</umdNm></item><item><aptDong>205</aptDong><aptNm>참누리아파트</aptNm><buildYear>2006</buildYear><buyerGbn>개인</buyerGbn><cdealDay> </cdealDay><cdealType> </cdealType><dealAmount>72,000</dealAmount><dealDay>30</dealDay><dealMonth>1</dealMonth><dealYear>2024</dealYear><dealingGbn>중개거래</dealingGbn><estateAgentSggNm>경기 의정부시, 서울 성북구</estateAgentSggNm><excluUseAr>84.98</excluUseAr><floor>3</floor><jibun>316-5</jibun><landLeaseholdGbn>N</landLeaseholdGbn><rgstDate>24.04.05</rgstDate><sggCd>11290</sggCd><slerGbn>개인</slerGbn><umdNm>장위동</umdNm></item><item><aptDong>217</aptDong><aptNm>길음뉴타운2단지푸르지오</aptNm><buildYear>2005</buildYear><buyerGbn>개인</buyerGbn><cdealDay> </cdealDay><cdealType> </cdealType><dealAmount>93,500</dealAmount><dealDay>27</dealDay><dealMonth>1</dealMonth><dealYear>2024</dealYear><dealingGbn>중개거래</dealingGbn><estateAgentSggNm>서울 성북구</estateAgentSggNm><excluUseAr>114.73</excluUseAr><floor>5</floor><jibun>1280</jibun><landLeaseholdGbn>N</landLeaseholdGbn><rgstDate>24.04.16</rgstDate><sggCd>11290</sggCd><slerGbn>개인</slerGbn><umdNm>길음동</umdNm></item><item><aptDong>104동</aptDong><aptNm>보문파크뷰자이</aptNm><buildYear>2017</buildYear><buyerGbn>개인</buyerGbn><cdealDay> </cdealDay><cdealType> </cdealType><dealAmount>87,000</dealAmount><dealDay>30</dealDay><dealMonth>1</dealMonth><dealYear>2024</dealYear><dealingGbn>중개거래</dealingGbn><estateAgentSggNm>서울 성북구</estateAgentSggNm><excluUseAr>59.19</excluUseAr><floor>11</floor><jibun>458</jibun><landLeaseholdGbn>N</landLeaseholdGbn><rgstDate>24.04.26</rgstDate><sggCd>11290</sggCd><slerGbn>법인</slerGbn><umdNm>보문동6가</umdNm></item><item><aptDong>212</aptDong><aptNm>길음뉴타운2단지푸르지오</aptNm><buildYear>2005</buildYear><buyerGbn>개인</buyerGbn><cdealDay> </cdealDay><cdealType> </cdealType><dealAmount>74,000</dealAmount><dealDay>29</dealDay><dealMonth>1</dealMonth><dealYear>2024</dealYear><dealingGbn>중개거래</dealingGbn><estateAgentSggNm>서울 성북구</estateAgentSggNm><excluUseAr>84.97</excluUseAr><floor>1</floor><jibun>1280</jibun><landLeaseholdGbn>N</landLeaseholdGbn><rgstDate>24.03.15</rgstDate><sggCd>11290</sggCd><slerGbn>개인</slerGbn><umdNm>길음동</umdNm></item><item><aptDong>102</aptDong><aptNm>래미안라센트</aptNm><buildYear>2011</buildYear><buyerGbn>개인</buyerGbn><cdealDay> </cdealDay><cdealType> </cdealType><dealAmount>112,000</dealAmount><dealDay>25</dealDay><dealMonth>1</dealMonth><dealYear>2024</dealYear><dealingGbn>중개거래</dealingGbn><estateAgentSggNm>서울 성북구</estateAgentSggNm><excluUseAr>84.99</excluUseAr><floor>18</floor><jibun>134</jibun><landLeaseholdGbn>N</landLeaseholdGbn><rgstDate>24.03.12</rgstDate><sggCd>11290</sggCd><slerGbn>개인</slerGbn><umdNm>종암동</umdNm></item><item><aptDong>401</aptDong><aptNm>길음뉴타운4단지(e편한세상)</aptNm><buildYear>2005</buildYear><buyerGbn>개인</buyerGbn><cdealDay> </cdealDay><cdealType> </cdealType><dealAmount>73,000</dealAmount><dealDay>24</dealDay><dealMonth>1</dealMonth><dealYear>2024</dealYear><dealingGbn>중개거래</dealingGbn><estateAgentSggNm>서울 성북구</estateAgentSggNm><excluUseAr>59.86</excluUseAr><floor>15</floor><jibun>1281</jibun><landLeaseholdGbn>N</landLeaseholdGbn><rgstDate>24.04.01</rgstDate><sggCd>11290</sggCd><slerGbn>개인</slerGbn><umdNm>길음동</umdNm></item><item><aptDong>203</aptDong><aptNm>길음뉴타운2단지푸르지오</aptNm><buildYear>2005</buildYear><buyerGbn>개인</buyerGbn><cdealDay> </cdealDay><cdealType> </cdealType><dealAmount>91,000</dealAmount><dealDay>18</dealDay><dealMonth>1</dealMonth><dealYear>2024</dealYear><dealingGbn>중개거래</dealingGbn><estateAgentSggNm>서울 성북구</estateAgentSggNm><excluUseAr>114.73</excluUseAr><floor>1</floor><jibun>1280</jibun><landLeaseholdGbn>N</landLeaseholdGbn><rgstDate>24.03.28</rgstDate><sggCd>11290</sggCd><slerGbn>개인</slerGbn><umdNm>길음동</umdNm></item><item><aptDong>103</aptDong><aptNm>월곡래미안루나밸리</aptNm><buildYear>2007</buildYear><buyerGbn>개인</buyerGbn><cdealDay> </cdealDay><cdealType> </cdealType><dealAmount>75,000</dealAmount><dealDay>20</dealDay><dealMonth>1</dealMonth><dealYear>2024</dealYear><dealingGbn>중개거래</dealingGbn><estateAgentSggNm>서울 성북구</estateAgentSggNm><excluUseAr>59.98</excluUseAr><floor>8</floor><jibun>226</jibun><landLeaseholdGbn>N</landLeaseholdGbn><rgstDate>24.02.14</rgstDate><sggCd>11290</sggCd><slerGbn>개인</slerGbn><umdNm>하월곡동</umdNm></item><item><aptDong>103</aptDong><aptNm>동일하이빌뉴시티</aptNm><buildYear>2011</buildYear><buyerGbn>개인</buyerGbn><cdealDay> </cdealDay><cdealType> </cdealType><dealAmount>104,700</dealAmount><dealDay>11</dealDay><dealMonth>1</dealMonth><dealYear>2024</dealYear><dealingGbn>중개거래</dealingGbn><estateAgentSggNm>서울 성북구</estateAgentSggNm><excluUseAr>126.6</excluUseAr><floor>14</floor><jibun>230</jibun><landLeaseholdGbn>N</landLeaseholdGbn><rgstDate>24.02.28</rgstDate><sggCd>11290</sggCd><slerGbn>개인</slerGbn><umdNm>하월곡동</umdNm></item><item><aptDong>111</aptDong><aptNm>월곡래미안루나밸리</aptNm><buildYear>2007</buildYear><buyerGbn>개인</buyerGbn><cdealDay> </cdealDay><cdealType> </cdealType><dealAmount>93,000</dealAmount><dealDay>28</dealDay><dealMonth>1</dealMonth><dealYear>2024</dealYear><dealingGbn>중개거래</dealingGbn><estateAgentSggNm>서울 성북구</estateAgentSggNm><excluUseAr>84.88</excluUseAr><floor>17</floor><jibun>226</jibun><landLeaseholdGbn>N</landLeaseholdGbn><rgstDate>24.04.05</rgstDate><sggCd>11290</sggCd><slerGbn>개인</slerGbn><umdNm>하월곡동</umdNm></item><item><aptDong>104</aptDong><aptNm>월곡래미안루나밸리</aptNm><buildYear>2007</buildYear><buyerGbn>개인</buyerGbn><cdealDay> </cdealDay><cdealType> </cdealType><dealAmount>79,500</dealAmount><dealDay>26</dealDay><dealMonth>1</dealMonth><dealYear>2024</dealYear><dealingGbn>중개거래</dealingGbn><estateAgentSggNm>서울 성북구</estateAgentSggNm><excluUseAr>59.98</excluUseAr><floor>12</floor><jibun>226</jibun><landLeaseholdGbn>N</landLeaseholdGbn><rgstDate>24.04.05</rgstDate><sggCd>11290</sggCd><slerGbn>개인</slerGbn><umdNm>하월곡동</umdNm></item><item><aptDong>111</aptDong><aptNm>월곡래미안루나밸리</aptNm><buildYear>2007</buildYear><buyerGbn>개인</buyerGbn><cdealDay> </cdealDay><cdealType> </cdealType><dealAmount>92,000</dealAmount><dealDay>10</dealDay><dealMonth>1</dealMonth><dealYear>2024</dealYear><dealingGbn>중개거래</dealingGbn><estateAgentSggNm>서울 성북구</estateAgentSggNm><excluUseAr>84.88</excluUseAr><floor>20</floor><jibun>226</jibun><landLeaseholdGbn>N</landLeaseholdGbn><rgstDate>24.07.26</rgstDate><sggCd>11290</sggCd><slerGbn>개인</slerGbn><umdNm>하월곡동</umdNm></item><item><aptDong> </aptDong><aptNm>삼선현대힐스테이트</aptNm><buildYear>2009</buildYear><buyerGbn>개인</buyerGbn><cdealDay>24.09.21</cdealDay><cdealType>O</cdealType><dealAmount>67,500</dealAmount><dealDay>20</dealDay><dealMonth>1</dealMonth><dealYear>2024</dealYear><dealingGbn>중개거래</dealingGbn><estateAgentSggNm>서울 성북구, 서울 종로구</estateAgentSggNm><excluUseAr>56.83</excluUseAr><floor>7</floor><jibun>420</jibun><landLeaseholdGbn>N</landLeaseholdGbn><rgstDate> </rgstDate><sggCd>11290</sggCd><slerGbn>개인</slerGbn><umdNm>삼선동2가</umdNm></item><item><aptDong>104</aptDong><aptNm>래미안포레카운티</aptNm><buildYear>2021</buildYear><buyerGbn>개인</buyerGbn><cdealDay> </cdealDay><cdealType> </cdealType><dealAmount>81,500</dealAmount><dealDay>22</dealDay><dealMonth>1</dealMonth><dealYear>2024</dealYear><dealingGbn>중개거래</dealingGbn><estateAgentSggNm>서울 성북구</estateAgentSggNm><excluUseAr>59.92</excluUseAr><floor>9</floor><jibun>322</jibun><landLeaseholdGbn>N</landLeaseholdGbn><rgstDate>24.03.13</rgstDate><sggCd>11290</sggCd><slerGbn>개인</slerGbn><umdNm>장위동</umdNm></item><item><aptDong>105</aptDong><aptNm>래미안아트리치</aptNm><buildYear>2019</buildYear><buyerGbn>개인</buyerGbn><cdealDay> </cdealDay><cdealType> </cdealType><dealAmount>100,000</dealAmount><dealDay>19</dealDay><dealMonth>1</dealMonth><dealYear>2024</dealYear><dealingGbn>중개거래</dealingGbn><estateAgentSggNm>서울 성북구</estateAgentSggNm><excluUseAr>84.98</excluUseAr><floor>19</floor><jibun>410</jibun><landLeaseholdGbn>N</landLeaseholdGbn><rgstDate>24.02.28</rgstDate><sggCd>11290</sggCd><slerGbn>개인</slerGbn><umdNm>석관동</umdNm></item><item><aptDong>114</aptDong><aptNm>이수브라운스톤돈암</aptNm><buildYear>2004</buildYear><buyerGbn>개인</buyerGbn><cdealDay> </cdealDay><cdealType> </cdealType><dealAmount>69,000</dealAmount><dealDay>23</dealDay><dealMonth>1</dealMonth><dealYear>2024</dealYear><dealingGbn>중개거래</dealingGbn><estateAgentSggNm>서울 성북구</estateAgentSggNm><excluUseAr>59.99</excluUseAr><floor>1</floor><jibun>636</jibun><landLeaseholdGbn>N</landLeaseholdGbn><rgstDate>24.04.29</rgstDate><sggCd>11290</sggCd><slerGbn>개인</slerGbn><umdNm>돈암동</umdNm></item><item><aptDong>113</aptDong><aptNm>롯데캐슬클라시아</aptNm><buildYear>2022</buildYear><buyerGbn>개인</buyerGbn><cdealDay> </cdealDay><cdealType> </cdealType><dealAmount>102,500</dealAmount><dealDay>24</dealDay><dealMonth>1</dealMonth><dealYear>2024</dealYear><dealingGbn>중개거래</dealingGbn><estateAgentSggNm>서울 성북구</estateAgentSggNm><excluUseAr>59.7812</excluUseAr><floor>21</floor><jibun>1289</jibun><landLeaseholdGbn>N</landLeaseholdGbn><rgstDate>24.02.15</rgstDate><sggCd>11290</sggCd><slerGbn>개인</slerGbn><umdNm>길음동</umdNm></item><item><aptDong>110</aptDong><aptNm>래미안포레카운티</aptNm><buildYear>2021</buildYear><buyerGbn>개인</buyerGbn><cdealDay> </cdealDay><cdealType> </cdealType><dealAmount>92,800</dealAmount><dealDay>23</dealDay><dealMonth>1</dealMonth><dealYear>2024</dealYear><dealingGbn>중개거래</dealingGbn><estateAgentSggNm>서울 동대문구, 서울 성북구</estateAgentSggNm><excluUseAr>84.98</excluUseAr><floor>17</floor><jibun>322</jibun><landLeaseholdGbn>N</landLeaseholdGbn><rgstDate>24.04.29</rgstDate><sggCd>11290</sggCd><slerGbn>개인</slerGbn><umdNm>장위동</umdNm></item><item><aptDong>제103동</aptDong><aptNm>정릉스카이쌍용아파트</aptNm><buildYear>1999</buildYear><buyerGbn>개인</buyerGbn><cdealDay> </cdealDay><cdealType> </cdealType><dealAmount>55,900</dealAmount><dealDay>29</dealDay><dealMonth>1</dealMonth><dealYear>2024</dealYear><dealingGbn>중개거래</dealingGbn><estateAgentSggNm>서울 성북구</estateAgentSggNm><excluUseAr>59.9</excluUseAr><floor>7</floor><jibun>1014</jibun><landLeaseholdGbn>N</landLeaseholdGbn><rgstDate>24.04.25</rgstDate><sggCd>11290</sggCd><slerGbn>개인</slerGbn><umdNm>정릉동</umdNm></item><item><aptDong>710</aptDong><aptNm>꿈의숲아이파크</aptNm><buildYear>2022</buildYear><buyerGbn>개인</buyerGbn><cdealDay> </cdealDay><cdealType> </cdealType><dealAmount>106,500</dealAmount><dealDay>25</dealDay><dealMonth>1</dealMonth><dealYear>2024</dealYear><dealingGbn>중개거래</dealingGbn><estateAgentSggNm>서울 성북구</estateAgentSggNm><excluUseAr>84.47</excluUseAr><floor>16</floor><jibun>323</jibun><landLeaseholdGbn>N</landLeaseholdGbn><rgstDate>24.03.22</rgstDate><sggCd>11290</sggCd><slerGbn>개인</slerGbn><umdNm>장위동</umdNm></item><item><aptDong>111</aptDong><aptNm>일신건영휴먼빌아파트</aptNm><buildYear>2005</buildYear><buyerGbn>개인</buyerGbn><cdealDay> </cdealDay><cdealType> </cdealType><dealAmount>72,000</dealAmount><dealDay>27</dealDay><dealMonth>1</dealMonth><dealYear>2024</dealYear><dealingGbn>중개거래</dealingGbn><estateAgentSggNm>서울 성북구</estateAgentSggNm><excluUseAr>84.98</excluUseAr><floor>14</floor><jibun>524</jibun><landLeaseholdGbn>N</landLeaseholdGbn><rgstDate>24.04.15</rgstDate><sggCd>11290</sggCd><slerGbn>개인</slerGbn><umdNm>돈암동</umdNm></item><item><aptDong>204</aptDong><aptNm>길음뉴타운2단지푸르지오</aptNm><buildYear>2005</buildYear><buyerGbn>개인</buyerGbn><cdealDay> </cdealDay><cdealType> </cdealType><dealAmount>65,000</dealAmount><dealDay>18</dealDay><dealMonth>1</dealMonth><dealYear>2024</dealYear><dealingGbn>중개거래</dealingGbn><estateAgentSggNm>서울 성북구</estateAgentSggNm><excluUseAr>59.99</excluUseAr><floor>5</floor><jibun>1280</jibun><landLeaseholdGbn>N</landLeaseholdGbn><rgstDate>24.03.29</rgstDate><sggCd>11290</sggCd><slerGbn>개인</slerGbn><umdNm>길음동</umdNm></item><item><aptDong>111</aptDong><aptNm>래미안크리시엘</aptNm><buildYear>2004</buildYear><buyerGbn>개인</buyerGbn><cdealDay> </cdealDay><cdealType> </cdealType><dealAmount>67,800</dealAmount><dealDay>19</dealDay><dealMonth>1</dealMonth><dealYear>2024</dealYear><dealingGbn>중개거래</dealingGbn><estateAgentSggNm>서울 성북구</estateAgentSggNm><excluUseAr>59.99</excluUseAr><floor>17</floor><jibun>80</jibun><landLeaseholdGbn>N</landLeaseholdGbn><rgstDate>24.03.25</rgstDate><sggCd>11290</sggCd><slerGbn>개인</slerGbn><umdNm>종암동</umdNm></item><item><aptDong>122</aptDong><aptNm>래미안월곡</aptNm><buildYear>2006</buildYear><buyerGbn>개인</buyerGbn><cdealDay> </cdealDay><cdealType> </cdealType><dealAmount>74,500</dealAmount><dealDay>19</dealDay><dealMonth>1</dealMonth><dealYear>2024</dealYear><dealingGbn>중개거래</dealingGbn><estateAgentSggNm>서울 성북구</estateAgentSggNm><excluUseAr>59.754</excluUseAr><floor>7</floor><jibun>225</jibun><landLeaseholdGbn>N</landLeaseholdGbn><rgstDate>24.04.30</rgstDate><sggCd>11290</sggCd><slerGbn>개인</slerGbn><umdNm>하월곡동</umdNm></item><item><aptDong>112</aptDong><aptNm>롯데캐슬클라시아</aptNm><buildYear>2022</buildYear><buyerGbn>개인</buyerGbn><cdealDay> </cdealDay><cdealType> </cdealType><dealAmount>135,000</dealAmount><dealDay>23</dealDay><dealMonth>1</dealMonth><dealYear>2024</dealYear><dealingGbn>중개거래</dealingGbn><estateAgentSggNm>서울 성북구</estateAgentSggNm><excluUseAr>84.9757</excluUseAr><floor>2</floor><jibun>1289</jibun><landLeaseholdGbn>N</landLeaseholdGbn><rgstDate>24.04.25</rgstDate><sggCd>11290</sggCd><slerGbn>개인</slerGbn><umdNm>길음동</umdNm></item><item><aptDong>102</aptDong><aptNm>삼선현대힐스테이트</aptNm><buildYear>2009</buildYear><buyerGbn>개인</buyerGbn><cdealDay> </cdealDay><cdealType> </cdealType><dealAmount>68,000</dealAmount><dealDay>20</dealDay><dealMonth>1</dealMonth><dealYear>2024</dealYear><dealingGbn>중개거래</dealingGbn><estateAgentSggNm>서울 성북구, 서울 종로구</estateAgentSggNm><excluUseAr>56.83</excluUseAr><floor>3</floor><jibun>420</jibun><landLeaseholdGbn>N</landLeaseholdGbn><rgstDate>24.03.27</rgstDate><sggCd>11290</sggCd><slerGbn>개인</slerGbn><umdNm>삼선동2가</umdNm></item><item><aptDong>115</aptDong><aptNm>래미안크리시엘</aptNm><buildYear>2004</buildYear><buyerGbn>개인</buyerGbn><cdealDay> </cdealDay><cdealType> </cdealType><dealAmount>78,000</dealAmount><dealDay>19</dealDay><dealMonth>1</dealMonth><dealYear>2024</dealYear><dealingGbn>중개거래</dealingGbn><estateAgentSggNm>서울 성북구</estateAgentSggNm><excluUseAr>84.95</excluUseAr><floor>6</floor><jibun>80</jibun><landLeaseholdGbn>N</landLeaseholdGbn><rgstDate>24.03.12</rgstDate><sggCd>11290</sggCd><slerGbn>개인</slerGbn><umdNm>종암동</umdNm></item><item><aptDong>207</aptDong><aptNm>참누리아파트</aptNm><buildYear>2006</buildYear><buyerGbn>개인</buyerGbn><cdealDay> </cdealDay><cdealType> </cdealType><dealAmount>74,700</dealAmount><dealDay>26</dealDay><dealMonth>1</dealMonth><dealYear>2024</dealYear><dealingGbn>중개거래</dealingGbn><estateAgentSggNm>서울 성북구</estateAgentSggNm><excluUseAr>84.89</excluUseAr><floor>8</floor><jibun>316-5</jibun><landLeaseholdGbn>N</landLeaseholdGbn><rgstDate>24.03.25</rgstDate><sggCd>11290</sggCd><slerGbn>개인</slerGbn><umdNm>장위동</umdNm></item><item><aptDong>116</aptDong><aptNm>래미안길음센터피스</aptNm><buildYear>2019</buildYear><buyerGbn>개인</buyerGbn><cdealDay> </cdealDay><cdealType> </cdealType><dealAmount>97,500</dealAmount><dealDay>13</dealDay><dealMonth>1</dealMonth><dealYear>2024</dealYear><dealingGbn>중개거래</dealingGbn><estateAgentSggNm>서울 성북구</estateAgentSggNm><excluUseAr>59.9</excluUseAr><floor>27</floor><jibun>1288</jibun><landLeaseholdGbn>N</landLeaseholdGbn><rgstDate>24.03.15</rgstDate><sggCd>11290</sggCd><slerGbn>개인</slerGbn><umdNm>길음동</umdNm></item><item><aptDong>114</aptDong><aptNm>래미안아트리치</aptNm><buildYear>2019</buildYear><buyerGbn>개인</buyerGbn><cdealDay> </cdealDay><cdealType> </cdealType><dealAmount>81,000</dealAmount><dealDay>13</dealDay><dealMonth>1</dealMonth><dealYear>2024</dealYear><dealingGbn>중개거래</dealingGbn><estateAgentSggNm>서울 성북구</estateAgentSggNm><excluUseAr>59.98</excluUseAr><floor>9</floor><jibun>410</jibun><landLeaseholdGbn>N</landLeaseholdGbn><rgstDate>24.03.08</rgstDate><sggCd>11290</sggCd><slerGbn>개인</slerGbn><umdNm>석관동</umdNm></item><item><aptDong>713</aptDong><aptNm>꿈의숲아이파크</aptNm><buildYear>2022</buildYear><buyerGbn>개인</buyerGbn><cdealDay> </cdealDay><cdealType> </cdealType><dealAmount>86,300</dealAmount><dealDay>22</dealDay><dealMonth>1</dealMonth><dealYear>2024</dealYear><dealingGbn>중개거래</dealingGbn><estateAgentSggNm>서울 성북구</estateAgentSggNm><excluUseAr>59.1</excluUseAr><floor>6</floor><jibun>323</jibun><landLeaseholdGbn>N</landLeaseholdGbn><rgstDate>24.06.05</rgstDate><sggCd>11290</sggCd><slerGbn>개인</slerGbn><umdNm>장위동</umdNm></item><item><aptDong>311</aptDong><aptNm>정릉힐스테이트3차</aptNm><buildYear>2008</buildYear><buyerGbn>개인</buyerGbn><cdealDay> </cdealDay><cdealType> </cdealType><dealAmount>70,000</dealAmount><dealDay>17</dealDay><dealMonth>1</dealMonth><dealYear>2024</dealYear><dealingGbn>직거래</dealingGbn><estateAgentSggNm> </estateAgentSggNm><excluUseAr>84.97</excluUseAr><floor>3</floor><jibun>1031</jibun><landLeaseholdGbn>N</landLeaseholdGbn><rgstDate>24.02.13</rgstDate><sggCd>11290</sggCd><slerGbn>개인</slerGbn><umdNm>정릉동</umdNm></item><item><aptDong>106</aptDong><aptNm>래미안아트리치</aptNm><buildYear>2019</buildYear><buyerGbn>개인</buyerGbn><cdealDay> </cdealDay><cdealType> </cdealType><dealAmount>102,000</dealAmount><dealDay>13</dealDay><dealMonth>1</dealMonth><dealYear>2024</dealYear><dealingGbn>중개거래</dealingGbn><estateAgentSggNm>서울 동대문구, 서울 성북구</estateAgentSggNm><excluUseAr>84.97</excluUseAr><floor>7</floor><jibun>410</jibun><landLeaseholdGbn>N</landLeaseholdGbn><rgstDate>24.03.29</rgstDate><sggCd>11290</sggCd><slerGbn>개인</slerGbn><umdNm>석관동</umdNm></item><item><aptDong>115</aptDong><aptNm>동아에코빌</aptNm><buildYear>2003</buildYear><buyerGbn>개인</buyerGbn><cdealDay> </cdealDay><cdealType> </cdealType><dealAmount>59,200</dealAmount><dealDay>23</dealDay><dealMonth>1</dealMonth><dealYear>2024</dealYear><dealingGbn>중개거래</dealingGbn><estateAgentSggNm>서울 성북구</estateAgentSggNm><excluUseAr>59.95</excluUseAr><floor>16</floor><jibun>101</jibun><landLeaseholdGbn>N</landLeaseholdGbn><rgstDate>24.03.29</rgstDate><sggCd>11290</sggCd><slerGbn>개인</slerGbn><umdNm>상월곡동</umdNm></item><item><aptDong>106</aptDong><aptNm>동아에코빌</aptNm><buildYear>2003</buildYear><buyerGbn>개인</buyerGbn><cdealDay> </cdealDay><cdealType> </cdealType><dealAmount>75,000</dealAmount><dealDay>16</dealDay><dealMonth>1</dealMonth><dealYear>2024</dealYear><dealingGbn>중개거래</dealingGbn><estateAgentSggNm>서울 성북구</estateAgentSggNm><excluUseAr>114.66</excluUseAr><floor>11</floor><jibun>101</jibun><landLeaseholdGbn>N</landLeaseholdGbn><rgstDate>24.03.12</rgstDate><sggCd>11290</sggCd><slerGbn>개인</slerGbn><umdNm>상월곡동</umdNm></item><item><aptDong>제101동</aptDong><aptNm>정릉스카이쌍용아파트</aptNm><buildYear>1999</buildYear><buyerGbn>개인</buyerGbn><cdealDay> </cdealDay><cdealType> </cdealType><dealAmount>56,000</dealAmount><dealDay>30</dealDay><dealMonth>1</dealMonth><dealYear>2024</dealYear><dealingGbn>중개거래</dealingGbn><estateAgentSggNm>서울 성북구</estateAgentSggNm><excluUseAr>59.9</excluUseAr><floor>8</floor><jibun>1014</jibun><landLeaseholdGbn>N</landLeaseholdGbn><rgstDate>24.03.15</rgstDate><sggCd>11290</sggCd><slerGbn>개인</slerGbn><umdNm>정릉동</umdNm></item><item><aptDong>209동</aptDong><aptNm>한진(609-1)</aptNm><buildYear>1998</buildYear><buyerGbn>개인</buyerGbn><cdealDay> </cdealDay><cdealType> </cdealType><dealAmount>52,800</dealAmount><dealDay>16</dealDay><dealMonth>1</dealMonth><dealYear>2024</dealYear><dealingGbn>중개거래</dealingGbn><estateAgentSggNm>서울 성북구</estateAgentSggNm><excluUseAr>59.58</excluUseAr><floor>5</floor><jibun>609-1</jibun><landLeaseholdGbn>N</landLeaseholdGbn><rgstDate>24.02.16</rgstDate><sggCd>11290</sggCd><slerGbn>개인</slerGbn><umdNm>돈암동</umdNm></item><item><aptDong>124</aptDong><aptNm>정릉풍림아이원</aptNm><buildYear>2005</buildYear><buyerGbn>개인</buyerGbn><cdealDay> </cdealDay><cdealType> </cdealType><dealAmount>44,300</dealAmount><dealDay>31</dealDay><dealMonth>1</dealMonth><dealYear>2024</dealYear><dealingGbn>중개거래</dealingGbn><estateAgentSggNm>서울 성북구</estateAgentSggNm><excluUseAr>59.88</excluUseAr><floor>1</floor><jibun>239</jibun><landLeaseholdGbn>N</landLeaseholdGbn><rgstDate>24.02.01</rgstDate><sggCd>11290</sggCd><slerGbn>개인</slerGbn><umdNm>정릉동</umdNm></item><item><aptDong>101</aptDong><aptNm>정릉힐스테이트</aptNm><buildYear>2004</buildYear><buyerGbn>개인</buyerGbn><cdealDay> </cdealDay><cdealType> </cdealType><dealAmount>79,000</dealAmount><dealDay>30</dealDay><dealMonth>1</dealMonth><dealYear>2024</dealYear><dealingGbn>중개거래</dealingGbn><estateAgentSggNm>서울 성북구</estateAgentSggNm><excluUseAr>84.92</excluUseAr><floor>14</floor><jibun>1025</jibun><landLeaseholdGbn>N</landLeaseholdGbn><rgstDate>24.03.21</rgstDate><sggCd>11290</sggCd><slerGbn>개인</slerGbn><umdNm>정릉동</umdNm></item><item><aptDong>101</aptDong><aptNm>삼부컨비니언</aptNm><buildYear>1998</buildYear><buyerGbn>개인</buyerGbn><cdealDay> </cdealDay><cdealType> </cdealType><dealAmount>56,950</dealAmount><dealDay>27</dealDay><dealMonth>1</dealMonth><dealYear>2024</dealYear><dealingGbn>중개거래</dealingGbn><estateAgentSggNm>서울 성북구</estateAgentSggNm><excluUseAr>59.94</excluUseAr><floor>7</floor><jibun>1276</jibun><landLeaseholdGbn>N</landLeaseholdGbn><rgstDate>24.03.06</rgstDate><sggCd>11290</sggCd><slerGbn>개인</slerGbn><umdNm>길음동</umdNm></item><item><aptDong>510</aptDong><aptNm>래미안장위퍼스트하이</aptNm><buildYear>2020</buildYear><buyerGbn>개인</buyerGbn><cdealDay> </cdealDay><cdealType> </cdealType><dealAmount>83,000</dealAmount><dealDay>11</dealDay><dealMonth>1</dealMonth><dealYear>2024</dealYear><dealingGbn>중개거래</dealingGbn><estateAgentSggNm>서울 성북구</estateAgentSggNm><excluUseAr>59.99</excluUseAr><floor>5</floor><jibun>320</jibun><landLeaseholdGbn>N</landLeaseholdGbn><rgstDate>24.03.29</rgstDate><sggCd>11290</sggCd><slerGbn>개인</slerGbn><umdNm>장위동</umdNm></item><item><aptDong>212</aptDong><aptNm>아이파크종암동2차</aptNm><buildYear>2005</buildYear><buyerGbn>개인</buyerGbn><cdealDay> </cdealDay><cdealType> </cdealType><dealAmount>84,000</dealAmount><dealDay>13</dealDay><dealMonth>1</dealMonth><dealYear>2024</dealYear><dealingGbn>중개거래</dealingGbn><estateAgentSggNm>서울 성북구</estateAgentSggNm><excluUseAr>84.73</excluUseAr><floor>9</floor><jibun>131</jibun><landLeaseholdGbn>N</landLeaseholdGbn><rgstDate>24.03.22</rgstDate><sggCd>11290</sggCd><slerGbn>개인</slerGbn><umdNm>종암동</umdNm></item><item><aptDong>104</aptDong><aptNm>돈암동삼성</aptNm><buildYear>1999</buildYear><buyerGbn>개인</buyerGbn><cdealDay> </cdealDay><cdealType> </cdealType><dealAmount>70,000</dealAmount><dealDay>16</dealDay><dealMonth>1</dealMonth><dealYear>2024</dealYear><dealingGbn>중개거래</dealingGbn><estateAgentSggNm>서울 성북구</estateAgentSggNm><excluUseAr>84.59</excluUseAr><floor>23</floor><jibun>15-1</jibun><landLeaseholdGbn>N</landLeaseholdGbn><rgstDate>24.04.11</rgstDate><sggCd>11290</sggCd><slerGbn>개인</slerGbn><umdNm>돈암동</umdNm></item><item><aptDong>1</aptDong><aptNm>중앙하이츠</aptNm><buildYear>1994</buildYear><buyerGbn>개인</buyerGbn><cdealDay> </cdealDay><cdealType> </cdealType><dealAmount>62,000</dealAmount><dealDay>30</dealDay><dealMonth>1</dealMonth><dealYear>2024</dealYear><dealingGbn>중개거래</dealingGbn><estateAgentSggNm>서울 성북구</estateAgentSggNm><excluUseAr>84.85</excluUseAr><floor>15</floor><jibun>110-2</jibun><landLeaseholdGbn>N</landLeaseholdGbn><rgstDate>24.04.29</rgstDate><sggCd>11290</sggCd><slerGbn>개인</slerGbn><umdNm>석관동</umdNm></item><item><aptDong>201</aptDong><aptNm>종암2차SKVIEW</aptNm><buildYear>2010</buildYear><buyerGbn>개인</buyerGbn><cdealDay> </cdealDay><cdealType> </cdealType><dealAmount>110,000</dealAmount><dealDay>27</dealDay><dealMonth>1</dealMonth><dealYear>2024</dealYear><dealingGbn>중개거래</dealingGbn><estateAgentSggNm>서울 성북구</estateAgentSggNm><excluUseAr>119.87</excluUseAr><floor>11</floor><jibun>135</jibun><landLeaseholdGbn>N</landLeaseholdGbn><rgstDate>24.04.29</rgstDate><sggCd>11290</sggCd><slerGbn>개인</slerGbn><umdNm>종암동</umdNm></item><item><aptDong>212</aptDong><aptNm>래미안세레니티</aptNm><buildYear>2009</buildYear><buyerGbn>개인</buyerGbn><cdealDay> </cdealDay><cdealType> </cdealType><dealAmount>89,700</dealAmount><dealDay>20</dealDay><dealMonth>1</dealMonth><dealYear>2024</dealYear><dealingGbn>중개거래</dealingGbn><estateAgentSggNm>서울 성북구</estateAgentSggNm><excluUseAr>84.99</excluUseAr><floor>12</floor><jibun>133</jibun><landLeaseholdGbn>N</landLeaseholdGbn><rgstDate>24.03.25</rgstDate><sggCd>11290</sggCd><slerGbn>개인</slerGbn><umdNm>종암동</umdNm></item><item><aptDong>411</aptDong><aptNm>길음뉴타운4단지(e편한세상)</aptNm><buildYear>2005</buildYear><buyerGbn>개인</buyerGbn><cdealDay> </cdealDay><cdealType> </cdealType><dealAmount>77,500</dealAmount><dealDay>13</dealDay><dealMonth>1</dealMonth><dealYear>2024</dealYear><dealingGbn>중개거래</dealingGbn><estateAgentSggNm>서울 성북구</estateAgentSggNm><excluUseAr>84.64</excluUseAr><floor>1</floor><jibun>1281</jibun><landLeaseholdGbn>N</landLeaseholdGbn><rgstDate>24.03.29</rgstDate><sggCd>11290</sggCd><slerGbn>개인</slerGbn><umdNm>길음동</umdNm></item><item><aptDong>104</aptDong><aptNm>정릉힐스테이트</aptNm><buildYear>2004</buildYear><buyerGbn>개인</buyerGbn><cdealDay> </cdealDay><cdealType> </cdealType><dealAmount>75,000</dealAmount><dealDay>9</dealDay><dealMonth>1</dealMonth><dealYear>2024</dealYear><dealingGbn>중개거래</dealingGbn><estateAgentSggNm>서울 강서구</estateAgentSggNm><excluUseAr>84.92</excluUseAr><floor>6</floor><jibun>1025</jibun><landLeaseholdGbn>N</landLeaseholdGbn><rgstDate>24.02.29</rgstDate><sggCd>11290</sggCd><slerGbn>개인</slerGbn><umdNm>정릉동</umdNm></item><item><aptDong>105</aptDong><aptNm>돈암코오롱하늘채</aptNm><buildYear>2016</buildYear><buyerGbn>개인</buyerGbn><cdealDay> </cdealDay><cdealType> </cdealType><dealAmount>98,000</dealAmount><dealDay>27</dealDay><dealMonth>1</dealMonth><dealYear>2024</dealYear><dealingGbn>중개거래</dealingGbn><estateAgentSggNm>서울 성북구</estateAgentSggNm><excluUseAr>84.8576</excluUseAr><floor>10</floor><jibun>644</jibun><landLeaseholdGbn>N</landLeaseholdGbn><rgstDate>24.02.02</rgstDate><sggCd>11290</sggCd><slerGbn>개인</slerGbn><umdNm>돈암동</umdNm></item><item><aptDong>101</aptDong><aptNm>극동</aptNm><buildYear>2000</buildYear><buyerGbn>개인</buyerGbn><cdealDay> </cdealDay><cdealType> </cdealType><dealAmount>63,000</dealAmount><dealDay>29</dealDay><dealMonth>1</dealMonth><dealYear>2024</dealYear><dealingGbn>중개거래</dealingGbn><estateAgentSggNm>서울 성북구</estateAgentSggNm><excluUseAr>59.67</excluUseAr><floor>6</floor><jibun>128</jibun><landLeaseholdGbn>N</landLeaseholdGbn><rgstDate>24.03.07</rgstDate><sggCd>11290</sggCd><slerGbn>개인</slerGbn><umdNm>종암동</umdNm></item><item><aptDong>107</aptDong><aptNm>한신</aptNm><buildYear>1998</buildYear><buyerGbn>개인</buyerGbn><cdealDay> </cdealDay><cdealType> </cdealType><dealAmount>64,500</dealAmount><dealDay>17</dealDay><dealMonth>1</dealMonth><dealYear>2024</dealYear><dealingGbn>중개거래</dealingGbn><estateAgentSggNm>서울 성북구</estateAgentSggNm><excluUseAr>68.13</excluUseAr><floor>8</floor><jibun>609-1</jibun><landLeaseholdGbn>N</landLeaseholdGbn><rgstDate>24.03.08</rgstDate><sggCd>11290</sggCd><slerGbn>개인</slerGbn><umdNm>돈암동</umdNm></item><item><aptDong> </aptDong><aptNm>동아에코빌</aptNm><buildYear>2003</buildYear><buyerGbn>개인</buyerGbn><cdealDay>24.02.02</cdealDay><cdealType>O</cdealType><dealAmount>59,200</dealAmount><dealDay>20</dealDay><dealMonth>1</dealMonth><dealYear>2024</dealYear><dealingGbn>중개거래</dealingGbn><estateAgentSggNm>서울 성북구</estateAgentSggNm><excluUseAr>59.95</excluUseAr><floor>16</floor><jibun>101</jibun><landLeaseholdGbn>N</landLeaseholdGbn><rgstDate> </rgstDate><sggCd>11290</sggCd><slerGbn>개인</slerGbn><umdNm>상월곡동</umdNm></item><item><aptDong>101</aptDong><aptNm>극동</aptNm><buildYear>2000</buildYear><buyerGbn>개인</buyerGbn><cdealDay> </cdealDay><cdealType> </cdealType><dealAmount>76,000</dealAmount><dealDay>29</dealDay><dealMonth>1</dealMonth><dealYear>2024</dealYear><dealingGbn>중개거래</dealingGbn><estateAgentSggNm>서울 성북구</estateAgentSggNm><excluUseAr>114.75</excluUseAr><floor>12</floor><jibun>128</jibun><landLeaseholdGbn>N</landLeaseholdGbn><rgstDate>24.03.07</rgstDate><sggCd>11290</sggCd><slerGbn>개인</slerGbn><umdNm>종암동</umdNm></item><item><aptDong>118</aptDong><aptNm>두산</aptNm><buildYear>1998</buildYear><buyerGbn>개인</buyerGbn><cdealDay> </cdealDay><cdealType> </cdealType><dealAmount>69,000</dealAmount><dealDay>20</dealDay><dealMonth>1</dealMonth><dealYear>2024</dealYear><dealingGbn>중개거래</dealingGbn><estateAgentSggNm>서울 성북구</estateAgentSggNm><excluUseAr>59.97</excluUseAr><floor>15</floor><jibun>10</jibun><landLeaseholdGbn>N</landLeaseholdGbn><rgstDate>24.03.27</rgstDate><sggCd>11290</sggCd><slerGbn>개인</slerGbn><umdNm>석관동</umdNm></item><item><aptDong>106</aptDong><aptNm>꿈의숲푸르지오</aptNm><buildYear>2010</buildYear><buyerGbn>개인</buyerGbn><cdealDay> </cdealDay><cdealType> </cdealType><dealAmount>69,000</dealAmount><dealDay>20</dealDay><dealMonth>1</dealMonth><dealYear>2024</dealYear><dealingGbn>중개거래</dealingGbn><estateAgentSggNm>서울 성북구</estateAgentSggNm><excluUseAr>59.65</excluUseAr><floor>10</floor><jibun>228</jibun><landLeaseholdGbn>N</landLeaseholdGbn><rgstDate>24.04.05</rgstDate><sggCd>11290</sggCd><slerGbn>개인</slerGbn><umdNm>하월곡동</umdNm></item><item><aptDong>107</aptDong><aptNm>길음뉴타운1단지(래미안길음1차)</aptNm><buildYear>2003</buildYear><buyerGbn>개인</buyerGbn><cdealDay> </cdealDay><cdealType> </cdealType><dealAmount>71,000</dealAmount><dealDay>8</dealDay><dealMonth>1</dealMonth><dealYear>2024</dealYear><dealingGbn>중개거래</dealingGbn><estateAgentSggNm>서울 성북구</estateAgentSggNm><excluUseAr>59.99</excluUseAr><floor>3</floor><jibun>1279</jibun><landLeaseholdGbn>N</landLeaseholdGbn><rgstDate>24.03.19</rgstDate><sggCd>11290</sggCd><slerGbn>개인</slerGbn><umdNm>길음동</umdNm></item><item><aptDong>119</aptDong><aptNm>월곡두산위브</aptNm><buildYear>2003</buildYear><buyerGbn>개인</buyerGbn><cdealDay> </cdealDay><cdealType> </cdealType><dealAmount>70,000</dealAmount><dealDay>25</dealDay><dealMonth>1</dealMonth><dealYear>2024</dealYear><dealingGbn>중개거래</dealingGbn><estateAgentSggNm>서울 성북구</estateAgentSggNm><excluUseAr>59.855</excluUseAr><floor>4</floor><jibun>222</jibun><landLeaseholdGbn>N</landLeaseholdGbn><rgstDate>24.03.12</rgstDate><sggCd>11290</sggCd><slerGbn>개인</slerGbn><umdNm>하월곡동</umdNm></item><item><aptDong>108</aptDong><aptNm>동부센트레빌</aptNm><buildYear>2003</buildYear><buyerGbn>개인</buyerGbn><cdealDay> </cdealDay><cdealType> </cdealType><dealAmount>83,700</dealAmount><dealDay>26</dealDay><dealMonth>1</dealMonth><dealYear>2024</dealYear><dealingGbn>중개거래</dealingGbn><estateAgentSggNm>서울 동대문구, 서울 성북구</estateAgentSggNm><excluUseAr>80.54</excluUseAr><floor>18</floor><jibun>633</jibun><landLeaseholdGbn>N</landLeaseholdGbn><rgstDate>24.03.08</rgstDate><sggCd>11290</sggCd><slerGbn>개인</slerGbn><umdNm>돈암동</umdNm></item><item><aptDong>115</aptDong><aptNm>월곡두산위브</aptNm><buildYear>2003</buildYear><buyerGbn>개인</buyerGbn><cdealDay> </cdealDay><cdealType> </cdealType><dealAmount>66,900</dealAmount><dealDay>20</dealDay><dealMonth>1</dealMonth><dealYear>2024</dealYear><dealingGbn>중개거래</dealingGbn><estateAgentSggNm>경기 하남시, 서울 성북구</estateAgentSggNm><excluUseAr>59.855</excluUseAr><floor>17</floor><jibun>222</jibun><landLeaseholdGbn>N</landLeaseholdGbn><rgstDate>24.02.22</rgstDate><sggCd>11290</sggCd><slerGbn>개인</slerGbn><umdNm>하월곡동</umdNm></item><item><aptDong>102</aptDong><aptNm>신동아파밀리에</aptNm><buildYear>2011</buildYear><buyerGbn>개인</buyerGbn><cdealDay> </cdealDay><cdealType> </cdealType><dealAmount>81,000</dealAmount><dealDay>11</dealDay><dealMonth>1</dealMonth><dealYear>2024</dealYear><dealingGbn>중개거래</dealingGbn><estateAgentSggNm>서울 성북구</estateAgentSggNm><excluUseAr>84.83</excluUseAr><floor>13</floor><jibun>408</jibun><landLeaseholdGbn>N</landLeaseholdGbn><rgstDate>24.03.15</rgstDate><sggCd>11290</sggCd><slerGbn>개인</slerGbn><umdNm>석관동</umdNm></item><item><aptDong>126</aptDong><aptNm>정릉풍림아이원</aptNm><buildYear>2005</buildYear><buyerGbn>개인</buyerGbn><cdealDay> </cdealDay><cdealType> </cdealType><dealAmount>53,500</dealAmount><dealDay>17</dealDay><dealMonth>1</dealMonth><dealYear>2024</dealYear><dealingGbn>중개거래</dealingGbn><estateAgentSggNm>서울 성북구</estateAgentSggNm><excluUseAr>59.88</excluUseAr><floor>13</floor><jibun>239</jibun><landLeaseholdGbn>N</landLeaseholdGbn><rgstDate>24.03.28</rgstDate><sggCd>11290</sggCd><slerGbn>개인</slerGbn><umdNm>정릉동</umdNm></item><item><aptDong>102</aptDong><aptNm>안암동삼성래미안</aptNm><buildYear>2005</buildYear><buyerGbn>개인</buyerGbn><cdealDay> </cdealDay><cdealType> </cdealType><dealAmount>70,000</dealAmount><dealDay>20</dealDay><dealMonth>1</dealMonth><dealYear>2024</dealYear><dealingGbn>중개거래</dealingGbn><estateAgentSggNm>서울 성북구</estateAgentSggNm><excluUseAr>59.6983</excluUseAr><floor>11</floor><jibun>361</jibun><landLeaseholdGbn>N</landLeaseholdGbn><rgstDate>24.02.22</rgstDate><sggCd>11290</sggCd><slerGbn>개인</slerGbn><umdNm>안암동1가</umdNm></item><item><aptDong>124</aptDong><aptNm>정릉풍림아이원</aptNm><buildYear>2005</buildYear><buyerGbn>개인</buyerGbn><cdealDay> </cdealDay><cdealType> </cdealType><dealAmount>49,500</dealAmount><dealDay>23</dealDay><dealMonth>1</dealMonth><dealYear>2024</dealYear><dealingGbn>중개거래</dealingGbn><estateAgentSggNm>서울 성북구</estateAgentSggNm><excluUseAr>59.88</excluUseAr><floor>12</floor><jibun>239</jibun><landLeaseholdGbn>N</landLeaseholdGbn><rgstDate>24.02.20</rgstDate><sggCd>11290</sggCd><slerGbn>개인</slerGbn><umdNm>정릉동</umdNm></item><item><aptDong>정릉 우성아파트 101</aptDong><aptNm>정릉우성아파트 101~105동</aptNm><buildYear>2000</buildYear><buyerGbn>개인</buyerGbn><cdealDay> </cdealDay><cdealType> </cdealType><dealAmount>37,000</dealAmount><dealDay>26</dealDay><dealMonth>1</dealMonth><dealYear>2024</dealYear><dealingGbn>중개거래</dealingGbn><estateAgentSggNm>서울 성북구</estateAgentSggNm><excluUseAr>46.65</excluUseAr><floor>14</floor><jibun>1020</jibun><landLeaseholdGbn>N</landLeaseholdGbn><rgstDate>24.01.26</rgstDate><sggCd>11290</sggCd><slerGbn>개인</slerGbn><umdNm>정릉동</umdNm></item><item><aptDong>110</aptDong><aptNm>래미안아트리치</aptNm><buildYear>2019</buildYear><buyerGbn>개인</buyerGbn><cdealDay> </cdealDay><cdealType> </cdealType><dealAmount>99,000</dealAmount><dealDay>13</dealDay><dealMonth>1</dealMonth><dealYear>2024</dealYear><dealingGbn>중개거래</dealingGbn><estateAgentSggNm>서울 성북구</estateAgentSggNm><excluUseAr>84.97</excluUseAr><floor>13</floor><jibun>410</jibun><landLeaseholdGbn>N</landLeaseholdGbn><rgstDate>24.04.03</rgstDate><sggCd>11290</sggCd><slerGbn>개인</slerGbn><umdNm>석관동</umdNm></item><item><aptDong>209동</aptDong><aptNm>한진(609-1)</aptNm><buildYear>1998</buildYear><buyerGbn>개인</buyerGbn><cdealDay> </cdealDay><cdealType> </cdealType><dealAmount>51,000</dealAmount><dealDay>19</dealDay><dealMonth>1</dealMonth><dealYear>2024</dealYear><dealingGbn>중개거래</dealingGbn><estateAgentSggNm>서울 성북구</estateAgentSggNm><excluUseAr>59.58</excluUseAr><floor>20</floor><jibun>609-1</jibun><landLeaseholdGbn>N</landLeaseholdGbn><rgstDate>24.02.08</rgstDate><sggCd>11290</sggCd><slerGbn>개인</slerGbn><umdNm>돈암동</umdNm></item><item><aptDong>103</aptDong><aptNm>신동아파밀리에</aptNm><buildYear>2011</buildYear><buyerGbn>개인</buyerGbn><cdealDay> </cdealDay><cdealType> </cdealType><dealAmount>75,000</dealAmount><dealDay>9</dealDay><dealMonth>1</dealMonth><dealYear>2024</dealYear><dealingGbn>중개거래</dealingGbn><estateAgentSggNm>서울 성북구</estateAgentSggNm><excluUseAr>84.92</excluUseAr><floor>1</floor><jibun>408</jibun><landLeaseholdGbn>N</landLeaseholdGbn><rgstDate>24.04.25</rgstDate><sggCd>11290</sggCd><slerGbn>개인</slerGbn><umdNm>석관동</umdNm></item><item><aptDong>210</aptDong><aptNm>래미안세레니티</aptNm><buildYear>2009</buildYear><buyerGbn>개인</buyerGbn><cdealDay> </cdealDay><cdealType> </cdealType><dealAmount>100,900</dealAmount><dealDay>11</dealDay><dealMonth>1</dealMonth><dealYear>2024</dealYear><dealingGbn>중개거래</dealingGbn><estateAgentSggNm>서울 성북구</estateAgentSggNm><excluUseAr>114.99</excluUseAr><floor>20</floor><jibun>133</jibun><landLeaseholdGbn>N</landLeaseholdGbn><rgstDate>24.03.22</rgstDate><sggCd>11290</sggCd><slerGbn>개인</slerGbn><umdNm>종암동</umdNm></item><item><aptDong>109</aptDong><aptNm>래미안크리시엘</aptNm><buildYear>2004</buildYear><buyerGbn>개인</buyerGbn><cdealDay> </cdealDay><cdealType> </cdealType><dealAmount>65,000</dealAmount><dealDay>12</dealDay><dealMonth>1</dealMonth><dealYear>2024</dealYear><dealingGbn>중개거래</dealingGbn><estateAgentSggNm>서울 성북구</estateAgentSggNm><excluUseAr>59.99</excluUseAr><floor>13</floor><jibun>80</jibun><landLeaseholdGbn>N</landLeaseholdGbn><rgstDate>24.03.29</rgstDate><sggCd>11290</sggCd><slerGbn>개인</slerGbn><umdNm>종암동</umdNm></item><item><aptDong>107</aptDong><aptNm>래미안아트리치</aptNm><buildYear>2019</buildYear><buyerGbn>개인</buyerGbn><cdealDay> </cdealDay><cdealType> </cdealType><dealAmount>78,000</dealAmount><dealDay>5</dealDay><dealMonth>1</dealMonth><dealYear>2024</dealYear><dealingGbn>중개거래</dealingGbn><estateAgentSggNm>서울 성북구</estateAgentSggNm><excluUseAr>59.96</excluUseAr><floor>11</floor><jibun>410</jibun><landLeaseholdGbn>N</landLeaseholdGbn><rgstDate>24.02.27</rgstDate><sggCd>11290</sggCd><slerGbn>개인</slerGbn><umdNm>석관동</umdNm></item><item><aptDong>123</aptDong><aptNm>정릉풍림아이원</aptNm><buildYear>2005</buildYear><buyerGbn>개인</buyerGbn><cdealDay> </cdealDay><cdealType> </cdealType><dealAmount>46,900</dealAmount><dealDay>9</dealDay><dealMonth>1</dealMonth><dealYear>2024</dealYear><dealingGbn>중개거래</dealingGbn><estateAgentSggNm>서울 성북구</estateAgentSggNm><excluUseAr>59.88</excluUseAr><floor>3</floor><jibun>239</jibun><landLeaseholdGbn>N</landLeaseholdGbn><rgstDate>24.03.26</rgstDate><sggCd>11290</sggCd><slerGbn>개인</slerGbn><umdNm>정릉동</umdNm></item><item><aptDong>111</aptDong><aptNm>길음동동부센트레빌(1278-0)</aptNm><buildYear>2003</buildYear><buyerGbn>개인</buyerGbn><cdealDay> </cdealDay><cdealType> </cdealType><dealAmount>75,300</dealAmount><dealDay>13</dealDay><dealMonth>1</dealMonth><dealYear>2024</dealYear><dealingGbn>중개거래</dealingGbn><estateAgentSggNm>서울 성북구</estateAgentSggNm><excluUseAr>84.844</excluUseAr><floor>1</floor><jibun>1278</jibun><landLeaseholdGbn>N</landLeaseholdGbn><rgstDate>24.04.15</rgstDate><sggCd>11290</sggCd><slerGbn>개인</slerGbn><umdNm>길음동</umdNm></item><item><aptDong>3</aptDong><aptNm>중앙하이츠</aptNm><buildYear>1994</buildYear><buyerGbn>개인</buyerGbn><cdealDay> </cdealDay><cdealType> </cdealType><dealAmount>47,800</dealAmount><dealDay>22</dealDay><dealMonth>1</dealMonth><dealYear>2024</dealYear><dealingGbn>중개거래</dealingGbn><estateAgentSggNm>경기 화성시, 서울 성북구</estateAgentSggNm><excluUseAr>59.79</excluUseAr><floor>5</floor><jibun>110-2</jibun><landLeaseholdGbn>N</landLeaseholdGbn><rgstDate>24.04.30</rgstDate><sggCd>11290</sggCd><slerGbn>개인</slerGbn><umdNm>석관동</umdNm></item><item><aptDong>118</aptDong><aptNm>래미안길음센터피스</aptNm><buildYear>2019</buildYear><buyerGbn>개인</buyerGbn><cdealDay> </cdealDay><cdealType> </cdealType><dealAmount>98,300</dealAmount><dealDay>19</dealDay><dealMonth>1</dealMonth><dealYear>2024</dealYear><dealingGbn>중개거래</dealingGbn><estateAgentSggNm>서울 성북구</estateAgentSggNm><excluUseAr>59.99</excluUseAr><floor>7</floor><jibun>1288</jibun><landLeaseholdGbn>N</landLeaseholdGbn><rgstDate>24.04.08</rgstDate><sggCd>11290</sggCd><slerGbn>개인</slerGbn><umdNm>길음동</umdNm></item><item><aptDong>111</aptDong><aptNm>일신건영휴먼빌아파트</aptNm><buildYear>2005</buildYear><buyerGbn>개인</buyerGbn><cdealDay> </cdealDay><cdealType> </cdealType><dealAmount>71,500</dealAmount><dealDay>23</dealDay><dealMonth>1</dealMonth><dealYear>2024</dealYear><dealingGbn>중개거래</dealingGbn><estateAgentSggNm>서울 성북구</estateAgentSggNm><excluUseAr>84.98</excluUseAr><floor>2</floor><jibun>524</jibun><landLeaseholdGbn>N</landLeaseholdGbn><rgstDate>24.02.26</rgstDate><sggCd>11290</sggCd><slerGbn>개인</slerGbn><umdNm>돈암동</umdNm></item><item><aptDong>123</aptDong><aptNm>정릉풍림아이원</aptNm><buildYear>2005</buildYear><buyerGbn>개인</buyerGbn><cdealDay> </cdealDay><cdealType> </cdealType><dealAmount>47,800</dealAmount><dealDay>12</dealDay><dealMonth>1</dealMonth><dealYear>2024</dealYear><dealingGbn>중개거래</dealingGbn><estateAgentSggNm>서울 성북구</estateAgentSggNm><excluUseAr>59.88</excluUseAr><floor>17</floor><jibun>239</jibun><landLeaseholdGbn>N</landLeaseholdGbn><rgstDate>24.03.26</rgstDate><sggCd>11290</sggCd><slerGbn>개인</slerGbn><umdNm>정릉동</umdNm></item><item><aptDong> </aptDong><aptNm>한신</aptNm><buildYear>1998</buildYear><buyerGbn>개인</buyerGbn><cdealDay>24.02.26</cdealDay><cdealType>O</cdealType><dealAmount>80,000</dealAmount><dealDay>10</dealDay><dealMonth>1</dealMonth><dealYear>2024</dealYear><dealingGbn>직거래</dealingGbn><estateAgentSggNm> </estateAgentSggNm><excluUseAr>132.96</excluUseAr><floor>3</floor><jibun>609-1</jibun><landLeaseholdGbn>N</landLeaseholdGbn><rgstDate> </rgstDate><sggCd>11290</sggCd><slerGbn>개인</slerGbn><umdNm>돈암동</umdNm></item><item><aptDong>110</aptDong><aptNm>길음뉴타운1단지(래미안길음1차)</aptNm><buildYear>2003</buildYear><buyerGbn>개인</buyerGbn><cdealDay> </cdealDay><cdealType> </cdealType><dealAmount>73,800</dealAmount><dealDay>9</dealDay><dealMonth>1</dealMonth><dealYear>2024</dealYear><dealingGbn>중개거래</dealingGbn><estateAgentSggNm>서울 성북구</estateAgentSggNm><excluUseAr>59.99</excluUseAr><floor>12</floor><jibun>1279</jibun><landLeaseholdGbn>N</landLeaseholdGbn><rgstDate>24.02.23</rgstDate><sggCd>11290</sggCd><slerGbn>개인</slerGbn><umdNm>길음동</umdNm></item><item><aptDong>103</aptDong><aptNm>래미안아트리치</aptNm><buildYear>2019</buildYear><buyerGbn>개인</buyerGbn><cdealDay> </cdealDay><cdealType> </cdealType><dealAmount>82,500</dealAmount><dealDay>8</dealDay><dealMonth>1</dealMonth><dealYear>2024</dealYear><dealingGbn>중개거래</dealingGbn><estateAgentSggNm>서울 성북구</estateAgentSggNm><excluUseAr>59.42</excluUseAr><floor>18</floor><jibun>410</jibun><landLeaseholdGbn>N</landLeaseholdGbn><rgstDate>24.01.30</rgstDate><sggCd>11290</sggCd><slerGbn>개인</slerGbn><umdNm>석관동</umdNm></item><item><aptDong>115</aptDong><aptNm>동아에코빌</aptNm><buildYear>2003</buildYear><buyerGbn>개인</buyerGbn><cdealDay> </cdealDay><cdealType> </cdealType><dealAmount>56,000</dealAmount><dealDay>15</dealDay><dealMonth>1</dealMonth><dealYear>2024</dealYear><dealingGbn>중개거래</dealingGbn><estateAgentSggNm>서울 성북구</estateAgentSggNm><excluUseAr>59.95</excluUseAr><floor>7</floor><jibun>101</jibun><landLeaseholdGbn>N</landLeaseholdGbn><rgstDate>24.02.28</rgstDate><sggCd>11290</sggCd><slerGbn>개인</slerGbn><umdNm>상월곡동</umdNm></item><item><aptDong>204동</aptDong><aptNm>한진(609-1)</aptNm><buildYear>1998</buildYear><buyerGbn>개인</buyerGbn><cdealDay> </cdealDay><cdealType> </cdealType><dealAmount>74,000</dealAmount><dealDay>13</dealDay><dealMonth>1</dealMonth><dealYear>2024</dealYear><dealingGbn>중개거래</dealingGbn><estateAgentSggNm>서울 성북구</estateAgentSggNm><excluUseAr>84.87</excluUseAr><floor>9</floor><jibun>609-1</jibun><landLeaseholdGbn>N</landLeaseholdGbn><rgstDate>24.04.19</rgstDate><sggCd>11290</sggCd><slerGbn>개인</slerGbn><umdNm>돈암동</umdNm></item><item><aptDong>102</aptDong><aptNm>길음역금호어울림센터힐</aptNm><buildYear>2014</buildYear><buyerGbn>개인</buyerGbn><cdealDay> </cdealDay><cdealType> </cdealType><dealAmount>77,500</dealAmount><dealDay>20</dealDay><dealMonth>1</dealMonth><dealYear>2024</dealYear><dealingGbn>중개거래</dealingGbn><estateAgentSggNm>서울 성북구</estateAgentSggNm><excluUseAr>59.84</excluUseAr><floor>17</floor><jibun>643</jibun><landLeaseholdGbn>N</landLeaseholdGbn><rgstDate>24.04.11</rgstDate><sggCd>11290</sggCd><slerGbn>개인</slerGbn><umdNm>돈암동</umdNm></item><item><aptDong>동소문현대아파트101동</aptDong><aptNm>동소문현대</aptNm><buildYear>1994</buildYear><buyerGbn>개인</buyerGbn><cdealDay> </cdealDay><cdealType> </cdealType><dealAmount>57,000</dealAmount><dealDay>4</dealDay><dealMonth>1</dealMonth><dealYear>2024</dealYear><dealingGbn>중개거래</dealingGbn><estateAgentSggNm>서울 성북구</estateAgentSggNm><excluUseAr>84.72</excluUseAr><floor>1</floor><jibun>630</jibun><landLeaseholdGbn>N</landLeaseholdGbn><rgstDate>24.03.04</rgstDate><sggCd>11290</sggCd><slerGbn>개인</slerGbn><umdNm>돈암동</umdNm></item><item><aptDong>110</aptDong><aptNm>두산</aptNm><buildYear>1998</buildYear><buyerGbn>개인</buyerGbn><cdealDay> </cdealDay><cdealType> </cdealType><dealAmount>65,800</dealAmount><dealDay>11</dealDay><dealMonth>1</dealMonth><dealYear>2024</dealYear><dealingGbn>중개거래</dealingGbn><estateAgentSggNm>서울 노원구, 서울 성북구</estateAgentSggNm><excluUseAr>59.97</excluUseAr><floor>10</floor><jibun>10</jibun><landLeaseholdGbn>N</landLeaseholdGbn><rgstDate>24.03.04</rgstDate><sggCd>11290</sggCd><slerGbn>개인</slerGbn><umdNm>석관동</umdNm></item><item><aptDong>102</aptDong><aptNm>아이파크종암동1차</aptNm><buildYear>2004</buildYear><buyerGbn>개인</buyerGbn><cdealDay> </cdealDay><cdealType> </cdealType><dealAmount>67,000</dealAmount><dealDay>12</dealDay><dealMonth>1</dealMonth><dealYear>2024</dealYear><dealingGbn>중개거래</dealingGbn><estateAgentSggNm>서울 성북구</estateAgentSggNm><excluUseAr>59.73</excluUseAr><floor>1</floor><jibun>130</jibun><landLeaseholdGbn>N</landLeaseholdGbn><rgstDate>24.04.30</rgstDate><sggCd>11290</sggCd><slerGbn>개인</slerGbn><umdNm>종암동</umdNm></item><item><aptDong>109</aptDong><aptNm>래미안길음센터피스</aptNm><buildYear>2019</buildYear><buyerGbn>개인</buyerGbn><cdealDay> </cdealDay><cdealType> </cdealType><dealAmount>134,000</dealAmount><dealDay>13</dealDay><dealMonth>1</dealMonth><dealYear>2024</dealYear><dealingGbn>중개거래</dealingGbn><estateAgentSggNm>서울 강북구</estateAgentSggNm><excluUseAr>84.99</excluUseAr><floor>14</floor><jibun>1288</jibun><landLeaseholdGbn>N</landLeaseholdGbn><rgstDate>24.04.01</rgstDate><sggCd>11290</sggCd><slerGbn>개인</slerGbn><umdNm>길음동</umdNm></item><item><aptDong>102</aptDong><aptNm>대우</aptNm><buildYear>2001</buildYear><buyerGbn>개인</buyerGbn><cdealDay> </cdealDay><cdealType> </cdealType><dealAmount>57,000</dealAmount><dealDay>22</dealDay><dealMonth>1</dealMonth><dealYear>2024</dealYear><dealingGbn>중개거래</dealingGbn><estateAgentSggNm>서울 성북구</estateAgentSggNm><excluUseAr>84.83</excluUseAr><floor>13</floor><jibun>1021</jibun><landLeaseholdGbn>N</landLeaseholdGbn><rgstDate>24.04.15</rgstDate><sggCd>11290</sggCd><slerGbn>개인</slerGbn><umdNm>정릉동</umdNm></item><item><aptDong>115</aptDong><aptNm>이수브라운스톤돈암</aptNm><buildYear>2004</buildYear><buyerGbn>개인</buyerGbn><cdealDay> </cdealDay><cdealType> </cdealType><dealAmount>94,500</dealAmount><dealDay>20</dealDay><dealMonth>1</dealMonth><dealYear>2024</dealYear><dealingGbn>중개거래</dealingGbn><estateAgentSggNm>서울 성북구</estateAgentSggNm><excluUseAr>114.89</excluUseAr><floor>6</floor><jibun>636</jibun><landLeaseholdGbn>N</landLeaseholdGbn><rgstDate>24.02.26</rgstDate><sggCd>11290</sggCd><slerGbn>개인</slerGbn><umdNm>돈암동</umdNm></item><item><aptDong>202동</aptDong><aptNm>한진(609-1)</aptNm><buildYear>1998</buildYear><buyerGbn>개인</buyerGbn><cdealDay> </cdealDay><cdealType> </cdealType><dealAmount>53,300</dealAmount><dealDay>12</dealDay><dealMonth>1</dealMonth><dealYear>2024</dealYear><dealingGbn>중개거래</dealingGbn><estateAgentSggNm>서울 성북구</estateAgentSggNm><excluUseAr>59.58</excluUseAr><floor>20</floor><jibun>609-1</jibun><landLeaseholdGbn>N</landLeaseholdGbn><rgstDate>24.02.26</rgstDate><sggCd>11290</sggCd><slerGbn>개인</slerGbn><umdNm>돈암동</umdNm></item><item><aptDong>107</aptDong><aptNm>돈암코오롱하늘채</aptNm><buildYear>2016</buildYear><buyerGbn>개인</buyerGbn><cdealDay> </cdealDay><cdealType> </cdealType><dealAmount>82,000</dealAmount><dealDay>18</dealDay><dealMonth>1</dealMonth><dealYear>2024</dealYear><dealingGbn>중개거래</dealingGbn><estateAgentSggNm>서울 성북구</estateAgentSggNm><excluUseAr>59.9342</excluUseAr><floor>11</floor><jibun>644</jibun><landLeaseholdGbn>N</landLeaseholdGbn><rgstDate>24.03.29</rgstDate><sggCd>11290</sggCd><slerGbn>개인</slerGbn><umdNm>돈암동</umdNm></item><item><aptDong>104</aptDong><aptNm>정릉푸르지오</aptNm><buildYear>2005</buildYear><buyerGbn>개인</buyerGbn><cdealDay> </cdealDay><cdealType> </cdealType><dealAmount>73,500</dealAmount><dealDay>19</dealDay><dealMonth>1</dealMonth><dealYear>2024</dealYear><dealingGbn>중개거래</dealingGbn><estateAgentSggNm>서울 성북구</estateAgentSggNm><excluUseAr>84.89</excluUseAr><floor>5</floor><jibun>406</jibun><landLeaseholdGbn>N</landLeaseholdGbn><rgstDate>24.03.29</rgstDate><sggCd>11290</sggCd><slerGbn>개인</slerGbn><umdNm>정릉동</umdNm></item><item><aptDong>607</aptDong><aptNm>길음뉴타운6단지(래미안)</aptNm><buildYear>2007</buildYear><buyerGbn>개인</buyerGbn><cdealDay> </cdealDay><cdealType> </cdealType><dealAmount>86,000</dealAmount><dealDay>11</dealDay><dealMonth>1</dealMonth><dealYear>2024</dealYear><dealingGbn>중개거래</dealingGbn><estateAgentSggNm>서울 성북구</estateAgentSggNm><excluUseAr>59.373</excluUseAr><floor>13</floor><jibun>1283</jibun><landLeaseholdGbn>N</landLeaseholdGbn><rgstDate>24.02.29</rgstDate><sggCd>11290</sggCd><slerGbn>개인</slerGbn><umdNm>길음동</umdNm></item><item><aptDong>112</aptDong><aptNm>월곡두산위브</aptNm><buildYear>2003</buildYear><buyerGbn>개인</buyerGbn><cdealDay> </cdealDay><cdealType> </cdealType><dealAmount>65,500</dealAmount><dealDay>6</dealDay><dealMonth>1</dealMonth><dealYear>2024</dealYear><dealingGbn>중개거래</dealingGbn><estateAgentSggNm>경기 하남시, 서울 성북구</estateAgentSggNm><excluUseAr>59.855</excluUseAr><floor>16</floor><jibun>222</jibun><landLeaseholdGbn>N</landLeaseholdGbn><rgstDate>24.03.29</rgstDate><sggCd>11290</sggCd><slerGbn>개인</slerGbn><umdNm>하월곡동</umdNm></item><item><aptDong>102</aptDong><aptNm>범양</aptNm><buildYear>1998</buildYear><buyerGbn>개인</buyerGbn><cdealDay> </cdealDay><cdealType> </cdealType><dealAmount>66,000</dealAmount><dealDay>10</dealDay><dealMonth>1</dealMonth><dealYear>2024</dealYear><dealingGbn>직거래</dealingGbn><estateAgentSggNm> </estateAgentSggNm><excluUseAr>84.92</excluUseAr><floor>12</floor><jibun>631</jibun><landLeaseholdGbn>N</landLeaseholdGbn><rgstDate>24.01.19</rgstDate><sggCd>11290</sggCd><slerGbn>개인</slerGbn><umdNm>돈암동</umdNm></item><item><aptDong>111</aptDong><aptNm>래미안크리시엘</aptNm><buildYear>2004</buildYear><buyerGbn>개인</buyerGbn><cdealDay> </cdealDay><cdealType> </cdealType><dealAmount>70,000</dealAmount><dealDay>9</dealDay><dealMonth>1</dealMonth><dealYear>2024</dealYear><dealingGbn>중개거래</dealingGbn><estateAgentSggNm>서울 성북구</estateAgentSggNm><excluUseAr>59.99</excluUseAr><floor>7</floor><jibun>80</jibun><landLeaseholdGbn>N</landLeaseholdGbn><rgstDate>24.02.27</rgstDate><sggCd>11290</sggCd><slerGbn>개인</slerGbn><umdNm>종암동</umdNm></item><item><aptDong>104</aptDong><aptNm>정릉풍림아이원</aptNm><buildYear>2005</buildYear><buyerGbn>개인</buyerGbn><cdealDay> </cdealDay><cdealType> </cdealType><dealAmount>55,000</dealAmount><dealDay>15</dealDay><dealMonth>1</dealMonth><dealYear>2024</dealYear><dealingGbn>중개거래</dealingGbn><estateAgentSggNm>서울 성북구</estateAgentSggNm><excluUseAr>84.09</excluUseAr><floor>8</floor><jibun>239</jibun><landLeaseholdGbn>N</landLeaseholdGbn><rgstDate>24.02.23</rgstDate><sggCd>11290</sggCd><slerGbn>개인</slerGbn><umdNm>정릉동</umdNm></item><item><aptDong>106</aptDong><aptNm>돈암현대아파트</aptNm><buildYear>1991</buildYear><buyerGbn>개인</buyerGbn><cdealDay> </cdealDay><cdealType> </cdealType><dealAmount>56,700</dealAmount><dealDay>15</dealDay><dealMonth>1</dealMonth><dealYear>2024</dealYear><dealingGbn>중개거래</dealingGbn><estateAgentSggNm>서울 성북구</estateAgentSggNm><excluUseAr>56.7</excluUseAr><floor>7</floor><jibun>1</jibun><landLeaseholdGbn>N</landLeaseholdGbn><rgstDate>24.05.24</rgstDate><sggCd>11290</sggCd><slerGbn>개인</slerGbn><umdNm>돈암동</umdNm></item><item><aptDong>108</aptDong><aptNm>롯데캐슬클라시아</aptNm><buildYear>2022</buildYear><buyerGbn>개인</buyerGbn><cdealDay> </cdealDay><cdealType> </cdealType><dealAmount>141,000</dealAmount><dealDay>11</dealDay><dealMonth>1</dealMonth><dealYear>2024</dealYear><dealingGbn>중개거래</dealingGbn><estateAgentSggNm>서울 성북구</estateAgentSggNm><excluUseAr>84.7694</excluUseAr><floor>22</floor><jibun>1289</jibun><landLeaseholdGbn>N</landLeaseholdGbn><rgstDate>24.03.26</rgstDate><sggCd>11290</sggCd><slerGbn>개인</slerGbn><umdNm>길음동</umdNm></item><item><aptDong>102</aptDong><aptNm>돈암동삼성</aptNm><buildYear>1999</buildYear><buyerGbn>개인</buyerGbn><cdealDay> </cdealDay><cdealType> </cdealType><dealAmount>70,000</dealAmount><dealDay>5</dealDay><dealMonth>1</dealMonth><dealYear>2024</dealYear><dealingGbn>중개거래</dealingGbn><estateAgentSggNm>서울 성북구</estateAgentSggNm><excluUseAr>84.59</excluUseAr><floor>5</floor><jibun>15-1</jibun><landLeaseholdGbn>N</landLeaseholdGbn><rgstDate>24.04.15</rgstDate><sggCd>11290</sggCd><slerGbn>개인</slerGbn><umdNm>돈암동</umdNm></item><item><aptDong> </aptDong><aptNm>길음뉴타운8단지(래미안)</aptNm><buildYear>2010</buildYear><buyerGbn>개인</buyerGbn><cdealDay>24.03.25</cdealDay><cdealType>O</cdealType><dealAmount>83,500</dealAmount><dealDay>2</dealDay><dealMonth>1</dealMonth><dealYear>2024</dealYear><dealingGbn>중개거래</dealingGbn><estateAgentSggNm>경기 군포시, 서울 성북구</estateAgentSggNm><excluUseAr>59.99</excluUseAr><floor>20</floor><jibun>1284</jibun><landLeaseholdGbn>N</landLeaseholdGbn><rgstDate> </rgstDate><sggCd>11290</sggCd><slerGbn>개인</slerGbn><umdNm>길음동</umdNm></item><item><aptDong> </aptDong><aptNm>래미안장위퍼스트하이</aptNm><buildYear>2020</buildYear><buyerGbn>개인</buyerGbn><cdealDay>24.01.31</cdealDay><cdealType>O</cdealType><dealAmount>83,000</dealAmount><dealDay>11</dealDay><dealMonth>1</dealMonth><dealYear>2024</dealYear><dealingGbn>중개거래</dealingGbn><estateAgentSggNm>서울 성북구</estateAgentSggNm><excluUseAr>59.99</excluUseAr><floor>5</floor><jibun>320</jibun><landLeaseholdGbn>N</landLeaseholdGbn><rgstDate> </rgstDate><sggCd>11290</sggCd><slerGbn>개인</slerGbn><umdNm>장위동</umdNm></item><item><aptDong>123</aptDong><aptNm>삼선푸르지오</aptNm><buildYear>2008</buildYear><buyerGbn>개인</buyerGbn><cdealDay> </cdealDay><cdealType> </cdealType><dealAmount>68,000</dealAmount><dealDay>8</dealDay><dealMonth>1</dealMonth><dealYear>2024</dealYear><dealingGbn>중개거래</dealingGbn><estateAgentSggNm>서울 성북구</estateAgentSggNm><excluUseAr>59.95</excluUseAr><floor>3</floor><jibun>425</jibun><landLeaseholdGbn>N</landLeaseholdGbn><rgstDate>24.01.30</rgstDate><sggCd>11290</sggCd><slerGbn>개인</slerGbn><umdNm>삼선동2가</umdNm></item><item><aptDong>105</aptDong><aptNm>일신건영휴먼빌아파트</aptNm><buildYear>2005</buildYear><buyerGbn>개인</buyerGbn><cdealDay> </cdealDay><cdealType> </cdealType><dealAmount>71,500</dealAmount><dealDay>15</dealDay><dealMonth>1</dealMonth><dealYear>2024</dealYear><dealingGbn>중개거래</dealingGbn><estateAgentSggNm>서울 성북구</estateAgentSggNm><excluUseAr>84.98</excluUseAr><floor>1</floor><jibun>524</jibun><landLeaseholdGbn>N</landLeaseholdGbn><rgstDate>24.02.28</rgstDate><sggCd>11290</sggCd><slerGbn>개인</slerGbn><umdNm>돈암동</umdNm></item><item><aptDong>115</aptDong><aptNm>래미안길음센터피스</aptNm><buildYear>2019</buildYear><buyerGbn>개인</buyerGbn><cdealDay> </cdealDay><cdealType> </cdealType><dealAmount>100,000</dealAmount><dealDay>10</dealDay><dealMonth>1</dealMonth><dealYear>2024</dealYear><dealingGbn>중개거래</dealingGbn><estateAgentSggNm>서울 성북구</estateAgentSggNm><excluUseAr>59.97</excluUseAr><floor>9</floor><jibun>1288</jibun><landLeaseholdGbn>N</landLeaseholdGbn><rgstDate>24.03.26</rgstDate><sggCd>11290</sggCd><slerGbn>개인</slerGbn><umdNm>길음동</umdNm></item><item><aptDong>215</aptDong><aptNm>길음뉴타운2단지푸르지오</aptNm><buildYear>2005</buildYear><buyerGbn>개인</buyerGbn><cdealDay> </cdealDay><cdealType> </cdealType><dealAmount>82,500</dealAmount><dealDay>6</dealDay><dealMonth>1</dealMonth><dealYear>2024</dealYear><dealingGbn>중개거래</dealingGbn><estateAgentSggNm>서울 성북구</estateAgentSggNm><excluUseAr>84.97</excluUseAr><floor>5</floor><jibun>1280</jibun><landLeaseholdGbn>N</landLeaseholdGbn><rgstDate>24.03.18</rgstDate><sggCd>11290</sggCd><slerGbn>개인</slerGbn><umdNm>길음동</umdNm></item><item><aptDong>106</aptDong><aptNm>삼선현대힐스테이트</aptNm><buildYear>2009</buildYear><buyerGbn>개인</buyerGbn><cdealDay> </cdealDay><cdealType> </cdealType><dealAmount>69,000</dealAmount><dealDay>4</dealDay><dealMonth>1</dealMonth><dealYear>2024</dealYear><dealingGbn>중개거래</dealingGbn><estateAgentSggNm>서울 성북구, 서울 종로구</estateAgentSggNm><excluUseAr>56.83</excluUseAr><floor>8</floor><jibun>420</jibun><landLeaseholdGbn>N</landLeaseholdGbn><rgstDate>24.02.23</rgstDate><sggCd>11290</sggCd><slerGbn>개인</slerGbn><umdNm>삼선동2가</umdNm></item><item><aptDong>114</aptDong><aptNm>래미안길음센터피스</aptNm><buildYear>2019</buildYear><buyerGbn>개인</buyerGbn><cdealDay> </cdealDay><cdealType> </cdealType><dealAmount>135,500</dealAmount><dealDay>2</dealDay><dealMonth>1</dealMonth><dealYear>2024</dealYear><dealingGbn>중개거래</dealingGbn><estateAgentSggNm>서울 성북구</estateAgentSggNm><excluUseAr>84.95</excluUseAr><floor>35</floor><jibun>1288</jibun><landLeaseholdGbn>N</landLeaseholdGbn><rgstDate>24.04.09</rgstDate><sggCd>11290</sggCd><slerGbn>개인</slerGbn><umdNm>길음동</umdNm></item><item><aptDong>101</aptDong><aptNm>래미안아트리치</aptNm><buildYear>2019</buildYear><buyerGbn>개인</buyerGbn><cdealDay> </cdealDay><cdealType> </cdealType><dealAmount>81,000</dealAmount><dealDay>6</dealDay><dealMonth>1</dealMonth><dealYear>2024</dealYear><dealingGbn>중개거래</dealingGbn><estateAgentSggNm>서울 성북구</estateAgentSggNm><excluUseAr>59.98</excluUseAr><floor>6</floor><jibun>410</jibun><landLeaseholdGbn>N</landLeaseholdGbn><rgstDate>24.03.05</rgstDate><sggCd>11290</sggCd><slerGbn>개인</slerGbn><umdNm>석관동</umdNm></item><item><aptDong> </aptDong><aptNm>돈암동삼성</aptNm><buildYear>1999</buildYear><buyerGbn>개인</buyerGbn><cdealDay>24.02.20</cdealDay><cdealType>O</cdealType><dealAmount>72,150</dealAmount><dealDay>9</dealDay><dealMonth>1</dealMonth><dealYear>2024</dealYear><dealingGbn>중개거래</dealingGbn><estateAgentSggNm>서울 성북구</estateAgentSggNm><excluUseAr>84.59</excluUseAr><floor>7</floor><jibun>15-1</jibun><landLeaseholdGbn>N</landLeaseholdGbn><rgstDate> </rgstDate><sggCd>11290</sggCd><slerGbn>개인</slerGbn><umdNm>돈암동</umdNm></item><item><aptDong>117</aptDong><aptNm>두산</aptNm><buildYear>1998</buildYear><buyerGbn>개인</buyerGbn><cdealDay> </cdealDay><cdealType> </cdealType><dealAmount>62,000</dealAmount><dealDay>10</dealDay><dealMonth>1</dealMonth><dealYear>2024</dealYear><dealingGbn>중개거래</dealingGbn><estateAgentSggNm>서울 성북구</estateAgentSggNm><excluUseAr>59.97</excluUseAr><floor>21</floor><jibun>10</jibun><landLeaseholdGbn>N</landLeaseholdGbn><rgstDate>24.01.24</rgstDate><sggCd>11290</sggCd><slerGbn>개인</slerGbn><umdNm>석관동</umdNm></item><item><aptDong>201</aptDong><aptNm>길음뉴타운2단지푸르지오</aptNm><buildYear>2005</buildYear><buyerGbn>개인</buyerGbn><cdealDay> </cdealDay><cdealType> </cdealType><dealAmount>66,400</dealAmount><dealDay>10</dealDay><dealMonth>1</dealMonth><dealYear>2024</dealYear><dealingGbn>중개거래</dealingGbn><estateAgentSggNm>서울 성북구</estateAgentSggNm><excluUseAr>59.99</excluUseAr><floor>11</floor><jibun>1280</jibun><landLeaseholdGbn>N</landLeaseholdGbn><rgstDate>24.01.31</rgstDate><sggCd>11290</sggCd><slerGbn>개인</slerGbn><umdNm>길음동</umdNm></item><item><aptDong>125</aptDong><aptNm>정릉풍림아이원</aptNm><buildYear>2005</buildYear><buyerGbn>개인</buyerGbn><cdealDay> </cdealDay><cdealType> </cdealType><dealAmount>48,400</dealAmount><dealDay>8</dealDay><dealMonth>1</dealMonth><dealYear>2024</dealYear><dealingGbn>중개거래</dealingGbn><estateAgentSggNm>서울 성북구</estateAgentSggNm><excluUseAr>59.88</excluUseAr><floor>3</floor><jibun>239</jibun><landLeaseholdGbn>N</landLeaseholdGbn><rgstDate>24.01.31</rgstDate><sggCd>11290</sggCd><slerGbn>개인</slerGbn><umdNm>정릉동</umdNm></item><item><aptDong>115</aptDong><aptNm>동아에코빌</aptNm><buildYear>2003</buildYear><buyerGbn>개인</buyerGbn><cdealDay> </cdealDay><cdealType> </cdealType><dealAmount>59,400</dealAmount><dealDay>10</dealDay><dealMonth>1</dealMonth><dealYear>2024</dealYear><dealingGbn>중개거래</dealingGbn><estateAgentSggNm>서울 성북구</estateAgentSggNm><excluUseAr>59.95</excluUseAr><floor>19</floor><jibun>101</jibun><landLeaseholdGbn>N</landLeaseholdGbn><rgstDate>24.02.29</rgstDate><sggCd>11290</sggCd><slerGbn>개인</slerGbn><umdNm>상월곡동</umdNm></item><item><aptDong> </aptDong><aptNm>대원아파트</aptNm><buildYear>2006</buildYear><buyerGbn>개인</buyerGbn><cdealDay> </cdealDay><cdealType> </cdealType><dealAmount>24,700</dealAmount><dealDay>10</dealDay><dealMonth>1</dealMonth><dealYear>2024</dealYear><dealingGbn>직거래</dealingGbn><estateAgentSggNm> </estateAgentSggNm><excluUseAr>82.73</excluUseAr><floor>3</floor><jibun>822-1</jibun><landLeaseholdGbn>N</landLeaseholdGbn><rgstDate>24.01.10</rgstDate><sggCd>11290</sggCd><slerGbn>개인</slerGbn><umdNm>정릉동</umdNm></item><item><aptDong>206</aptDong><aptNm>길음뉴타운2단지푸르지오</aptNm><buildYear>2005</buildYear><buyerGbn>개인</buyerGbn><cdealDay> </cdealDay><cdealType> </cdealType><dealAmount>87,000</dealAmount><dealDay>8</dealDay><dealMonth>1</dealMonth><dealYear>2024</dealYear><dealingGbn>직거래</dealingGbn><estateAgentSggNm> </estateAgentSggNm><excluUseAr>143.43</excluUseAr><floor>14</floor><jibun>1280</jibun><landLeaseholdGbn>N</landLeaseholdGbn><rgstDate>24.01.09</rgstDate><sggCd>11290</sggCd><slerGbn>개인</slerGbn><umdNm>길음동</umdNm></item><item><aptDong>128</aptDong><aptNm>정릉풍림아이원</aptNm><buildYear>2005</buildYear><buyerGbn>개인</buyerGbn><cdealDay> </cdealDay><cdealType> </cdealType><dealAmount>56,000</dealAmount><dealDay>4</dealDay><dealMonth>1</dealMonth><dealYear>2024</dealYear><dealingGbn>중개거래</dealingGbn><estateAgentSggNm>서울 성북구</estateAgentSggNm><excluUseAr>60</excluUseAr><floor>10</floor><jibun>239</jibun><landLeaseholdGbn>N</landLeaseholdGbn><rgstDate>24.02.14</rgstDate><sggCd>11290</sggCd><slerGbn>개인</slerGbn><umdNm>정릉동</umdNm></item><item><aptDong>102</aptDong><aptNm>일신건영휴먼빌아파트</aptNm><buildYear>2005</buildYear><buyerGbn>개인</buyerGbn><cdealDay> </cdealDay><cdealType> </cdealType><dealAmount>112,500</dealAmount><dealDay>4</dealDay><dealMonth>1</dealMonth><dealYear>2024</dealYear><dealingGbn>중개거래</dealingGbn><estateAgentSggNm>서울 성북구</estateAgentSggNm><excluUseAr>143.51</excluUseAr><floor>13</floor><jibun>524</jibun><landLeaseholdGbn>N</landLeaseholdGbn><rgstDate>24.03.29</rgstDate><sggCd>11290</sggCd><slerGbn>법인</slerGbn><umdNm>돈암동</umdNm></item></items><numOfRows>100</numOfRows><pageNo>1</pageNo><totalCount>138</totalCount></body></response>