{
  "KeyStatisticList": {
    "list_total_count": 101,
    "row_count": 100,
    "row": [
      {
        "CLASS_NAME": "시장금리",
        "KEYSTAT_NAME": "한국은행 기준금리",
        "DATA_VALUE": "2.5",
        "CYCLE": "20250622",
        "UNIT_NAME": "%"
      },
      {
        "CLASS_NAME": "시장금리",
        "KEYSTAT_NAME": "콜금리(익일물)",
        "DATA_VALUE": "2.528",
        "CYCLE": "20250624",
        "UNIT_NAME": "%"
      },
      {
        "CLASS_NAME": "시장금리",
        "KEYSTAT_NAME": "KORIBOR(3개월)",
        "DATA_VALUE": "2.56",
        "CYCLE": "20250624",
        "UNIT_NAME": "%"
      },
      {
        "CLASS_NAME": "시장금리",
        "KEYSTAT_NAME": "CD수익률(91일)",
        "DATA_VALUE": "2.57",
        "CYCLE": "20250624",
        "UNIT_NAME": "%"
      },
      {
        "CLASS_NAME": "시장금리",
        "KEYSTAT_NAME": "통안증권수익률(364일)",
        "DATA_VALUE": "2.305",
        "CYCLE": "20250624",
        "UNIT_NAME": "%"
      },
      {
        "CLASS_NAME": "시장금리",
        "KEYSTAT_NAME": "국고채수익률(3년)",
        "DATA_VALUE": "2.461",
        "CYCLE": "20250624",
        "UNIT_NAME": "%"
      },
      {
        "CLASS_NAME": "시장금리",
        "KEYSTAT_NAME": "국고채수익률(5년)",
        "DATA_VALUE": "2.616",
        "CYCLE": "20250624",
        "UNIT_NAME": "%"
      },
      {
        "CLASS_NAME": "시장금리",
        "KEYSTAT_NAME": "회사채수익률(3년,AA-)",
        "DATA_VALUE": "2.983",
        "CYCLE": "20250624",
        "UNIT_NAME": "%"
      },
      {
        "CLASS_NAME": "여수신금리",
        "KEYSTAT_NAME": "예금은행 수신금리",
        "DATA_VALUE": "2.71",
        "CYCLE": "202504",
        "UNIT_NAME": "%"
      },
      {
        "CLASS_NAME": "여수신금리",
        "KEYSTAT_NAME": "예금은행 대출금리",
        "DATA_VALUE": "4.19",
        "CYCLE": "202504",
        "UNIT_NAME": "%"
      },
      {
        "CLASS_NAME": "예금/대출금",
        "KEYSTAT_NAME": "예금은행총예금(말잔)",
        "DATA_VALUE": "2092132.5",
        "CYCLE": "202504",
        "UNIT_NAME": "십억원"
      },
      {
        "CLASS_NAME": "예금/대출금",
        "KEYSTAT_NAME": "예금은행대출금(말잔)",
        "DATA_VALUE": "2428477.2",
        "CYCLE": "202504",
        "UNIT_NAME": "십억원"
      },
      {
        "CLASS_NAME": "예금/대출금",
        "KEYSTAT_NAME": "가계신용",
        "DATA_VALUE": "1928734.5",
        "CYCLE": "2025Q1",
        "UNIT_NAME": "십억원"
      },
      {
        "CLASS_NAME": "예금/대출금",
        "KEYSTAT_NAME": "가계대출연체율",
        "DATA_VALUE": "0.5",
        "CYCLE": "202504",
        "UNIT_NAME": "%"
      },
      {
        "CLASS_NAME": "통화량",
        "KEYSTAT_NAME": "M1(협의통화, 평잔)",
        "DATA_VALUE": "1284331.6",
        "CYCLE": "202504",
        "UNIT_NAME": "십억원"
      },
      {
        "CLASS_NAME": "통화량",
        "KEYSTAT_NAME": "M2(광의통화, 평잔)",
        "DATA_VALUE": "4240955.7",
        "CYCLE": "202504",
        "UNIT_NAME": "십억원"
      },
      {
        "CLASS_NAME": "통화량",
        "KEYSTAT_NAME": "Lf(평잔)",
        "DATA_VALUE": "5793784",
        "CYCLE": "202504",
        "UNIT_NAME": "십억원"
      },
      {
        "CLASS_NAME": "통화량",
        "KEYSTAT_NAME": "L(말잔)",
        "DATA_VALUE": "7261207.1",
        "CYCLE": "202504",
        "UNIT_NAME": "십억원"
      },
      {
        "CLASS_NAME": "환율",
        "KEYSTAT_NAME": "원/달러 환율(종가)",
        "DATA_VALUE": "1360.2",
        "CYCLE": "20250624",
        "UNIT_NAME": "원"
      },
      {
        "CLASS_NAME": "환율",
        "KEYSTAT_NAME": "원/엔(100엔) 환율(매매기준율)",
        "DATA_VALUE": "941.9",
        "CYCLE": "20250625",
        "UNIT_NAME": "원"
      },
      {
        "CLASS_NAME": "환율",
        "KEYSTAT_NAME": "원/유로 환율(매매기준율)",
        "DATA_VALUE": "1584.77",
        "CYCLE": "20250625",
        "UNIT_NAME": "원"
      },
      {
        "CLASS_NAME": "환율",
        "KEYSTAT_NAME": "원/위안 환율(종가)",
        "DATA_VALUE": "189.64",
        "CYCLE": "20250624",
        "UNIT_NAME": "원"
      },
      {
        "CLASS_NAME": "주식",
        "KEYSTAT_NAME": "코스피지수",
        "DATA_VALUE": "3103.64",
        "CYCLE": "20250624",
        "UNIT_NAME": "1980.01.04=100 "
      },
      {
        "CLASS_NAME": "주식",
        "KEYSTAT_NAME": "코스닥지수",
        "DATA_VALUE": "800.93",
        "CYCLE": "20250624",
        "UNIT_NAME": "1996.07.01=1000"
      },
      {
        "CLASS_NAME": "주식",
        "KEYSTAT_NAME": "주식거래대금(KOSPI)",
        "DATA_VALUE": "174.1",
        "CYCLE": "202504",
        "UNIT_NAME": "조원"
      },
      {
        "CLASS_NAME": "주식",
        "KEYSTAT_NAME": "투자자예탁금",
        "DATA_VALUE": "57.3",
        "CYCLE": "202505",
        "UNIT_NAME": "조원"
      },
      {
        "CLASS_NAME": "채권",
        "KEYSTAT_NAME": "채권거래대금",
        "DATA_VALUE": "155.4",
        "CYCLE": "202505",
        "UNIT_NAME": "조원"
      },
      {
        "CLASS_NAME": "채권",
        "KEYSTAT_NAME": "국고채발행액",
        "DATA_VALUE": "28502",
        "CYCLE": "202504",
        "UNIT_NAME": "십억원"
      },
      {
        "CLASS_NAME": "성장률",
        "KEYSTAT_NAME": "경제성장률(실질, 계절조정 전기대비)",
        "DATA_VALUE": "-0.2",
        "CYCLE": "2025Q1",
        "UNIT_NAME": "%"
      },
      {
        "CLASS_NAME": "성장률",
        "KEYSTAT_NAME": "민간소비증감률(실질, 계절조정 전기대비)",
        "DATA_VALUE": "-0.1",
        "CYCLE": "2025Q1",
        "UNIT_NAME": "%"
      },
      {
        "CLASS_NAME": "성장률",
        "KEYSTAT_NAME": "설비투자증감률(실질, 계절조정 전기대비)",
        "DATA_VALUE": "-0.4",
        "CYCLE": "2025Q1",
        "UNIT_NAME": "%"
      },
      {
        "CLASS_NAME": "성장률",
        "KEYSTAT_NAME": "건설투자증감률(실질, 계절조정 전기대비)",
        "DATA_VALUE": "-3.1",
        "CYCLE": "2025Q1",
        "UNIT_NAME": "%"
      },
      {
        "CLASS_NAME": "성장률",
        "KEYSTAT_NAME": "재화의 수출 증감률(실질, 계절조정 전기대비)",
        "DATA_VALUE": "-1.5",
        "CYCLE": "2025Q1",
        "UNIT_NAME": "%"
      },
      {
        "CLASS_NAME": "소득",
        "KEYSTAT_NAME": "GDP(명목, 계절조정)",
        "DATA_VALUE": "647226.7",
        "CYCLE": "2025Q1",
        "UNIT_NAME": "십억원"
      },
      {
        "CLASS_NAME": "소득",
        "KEYSTAT_NAME": "1인당GNI",
        "DATA_VALUE": "36745.4",
        "CYCLE": "2024",
        "UNIT_NAME": "달러"
      },
      {
        "CLASS_NAME": "GDP대비 비율",
        "KEYSTAT_NAME": "총저축률",
        "DATA_VALUE": "34.9",
        "CYCLE": "2025Q1",
        "UNIT_NAME": "%"
      },
      {
        "CLASS_NAME": "GDP대비 비율",
        "KEYSTAT_NAME": "국내총투자율",
        "DATA_VALUE": "28.9",
        "CYCLE": "2025Q1",
        "UNIT_NAME": "%"
      },
      {
        "CLASS_NAME": "GDP대비 비율",
        "KEYSTAT_NAME": "수출입의 대 GNI 비율",
        "DATA_VALUE": "89.6",
        "CYCLE": "2024",
        "UNIT_NAME": "%"
      },
      {
        "CLASS_NAME": "생산",
        "KEYSTAT_NAME": "전산업생산지수",
        "DATA_VALUE": "113.5",
        "CYCLE": "202504",
        "UNIT_NAME": "2020=100"
      },
      {
        "CLASS_NAME": "생산",
        "KEYSTAT_NAME": "제조업생산지수",
        "DATA_VALUE": "114",
        "CYCLE": "202504",
        "UNIT_NAME": "2020=100"
      },
      {
        "CLASS_NAME": "생산",
        "KEYSTAT_NAME": "제조업출하지수",
        "DATA_VALUE": "101.7",
        "CYCLE": "202504",
        "UNIT_NAME": "2020=100"
      },
      {
        "CLASS_NAME": "생산",
        "KEYSTAT_NAME": "제조업재고지수",
        "DATA_VALUE": "104",
        "CYCLE": "202504",
        "UNIT_NAME": "2020=100"
      },
      {
        "CLASS_NAME": "생산",
        "KEYSTAT_NAME": "제조업가동률지수",
        "DATA_VALUE": "103.8",
        "CYCLE": "202504",
        "UNIT_NAME": "2020=100"
      },
      {
        "CLASS_NAME": "생산",
        "KEYSTAT_NAME": "서비스업생산지수",
        "DATA_VALUE": "118.2",
        "CYCLE": "202504",
        "UNIT_NAME": "2020=100"
      },
      {
        "CLASS_NAME": "생산",
        "KEYSTAT_NAME": "도소매업생산지수",
        "DATA_VALUE": "105",
        "CYCLE": "202504",
        "UNIT_NAME": "2020=100"
      },
      {
        "CLASS_NAME": "소비",
        "KEYSTAT_NAME": "소매판매액지수",
        "DATA_VALUE": "101.4",
        "CYCLE": "202504",
        "UNIT_NAME": "2020=100"
      },
      {
        "CLASS_NAME": "소비",
        "KEYSTAT_NAME": "개인신용카드사용액",
        "DATA_VALUE": "73276893",
        "CYCLE": "202503",
        "UNIT_NAME": "백만원"
      },
      {
        "CLASS_NAME": "소비",
        "KEYSTAT_NAME": "자동차판매액지수",
        "DATA_VALUE": "111.5",
        "CYCLE": "202504",
        "UNIT_NAME": "2020=100"
      },
      {
        "CLASS_NAME": "투자",
        "KEYSTAT_NAME": "설비투자지수",
        "DATA_VALUE": "118.6",
        "CYCLE": "202504",
        "UNIT_NAME": "2015=100"
      },
      {
        "CLASS_NAME": "투자",
        "KEYSTAT_NAME": "설비용 기계류내수출하지수",
        "DATA_VALUE": "102.4",
        "CYCLE": "202504",
        "UNIT_NAME": "2020=100"
      },
      {
        "CLASS_NAME": "투자",
        "KEYSTAT_NAME": "국내기계수주액",
        "DATA_VALUE": "3.8",
        "CYCLE": "202504",
        "UNIT_NAME": "조원"
      },
      {
        "CLASS_NAME": "투자",
        "KEYSTAT_NAME": "건설기성액",
        "DATA_VALUE": "9.5",
        "CYCLE": "202504",
        "UNIT_NAME": "조원"
      },
      {
        "CLASS_NAME": "투자",
        "KEYSTAT_NAME": "건축허가면적",
        "DATA_VALUE": "9144.37",
        "CYCLE": "202504",
        "UNIT_NAME": "천㎡ "
      },
      {
        "CLASS_NAME": "투자",
        "KEYSTAT_NAME": "건설수주액",
        "DATA_VALUE": "12.1",
        "CYCLE": "202504",
        "UNIT_NAME": "조원"
      },
      {
        "CLASS_NAME": "투자",
        "KEYSTAT_NAME": "건축착공면적",
        "DATA_VALUE": "8490.39",
        "CYCLE": "202504",
        "UNIT_NAME": "천㎡ "
      },
      {
        "CLASS_NAME": "경기순환지표",
        "KEYSTAT_NAME": "동행지수순환변동치",
        "DATA_VALUE": "98.9",
        "CYCLE": "202504",
        "UNIT_NAME": "2020=100"
      },
      {
        "CLASS_NAME": "경기순환지표",
        "KEYSTAT_NAME": "선행지수순환변동치",
        "DATA_VALUE": "100.9",
        "CYCLE": "202504",
        "UNIT_NAME": "2020=100"
      },
      {
        "CLASS_NAME": "심리지표",
        "KEYSTAT_NAME": "전산업 기업심리지수실적",
        "DATA_VALUE": "90.7",
        "CYCLE": "202505",
        "UNIT_NAME": null
      },
      {
        "CLASS_NAME": "심리지표",
        "KEYSTAT_NAME": "소비자심리지수",
        "DATA_VALUE": "108.7",
        "CYCLE": "202506",
        "UNIT_NAME": null
      },
      {
        "CLASS_NAME": "심리지표",
        "KEYSTAT_NAME": "경제심리지수",
        "DATA_VALUE": "92.2",
        "CYCLE": "202505",
        "UNIT_NAME": null
      },
      {
        "CLASS_NAME": "기업경영지표",
        "KEYSTAT_NAME": "제조업매출액증감률",
        "DATA_VALUE": "-2.27",
        "CYCLE": "2023",
        "UNIT_NAME": "%"
      },
      {
        "CLASS_NAME": "기업경영지표",
        "KEYSTAT_NAME": "제조업매출액세전순이익률",
        "DATA_VALUE": "4.81",
        "CYCLE": "2023",
        "UNIT_NAME": "%"
      },
      {
        "CLASS_NAME": "기업경영지표",
        "KEYSTAT_NAME": "제조업부채비율",
        "DATA_VALUE": "75.87",
        "CYCLE": "2023",
        "UNIT_NAME": "%"
      },
      {
        "CLASS_NAME": "가계",
        "KEYSTAT_NAME": "가구당월평균소득",
        "DATA_VALUE": "6969.4",
        "CYCLE": "2024Q4",
        "UNIT_NAME": "천원"
      },
      {
        "CLASS_NAME": "가계",
        "KEYSTAT_NAME": "평균소비성향",
        "DATA_VALUE": "68.1",
        "CYCLE": "2024Q4",
        "UNIT_NAME": "%"
      },
      {
        "CLASS_NAME": "소득분배지표",
        "KEYSTAT_NAME": "지니계수",
        "DATA_VALUE": "0.323",
        "CYCLE": "2023",
        "UNIT_NAME": null
      },
      {
        "CLASS_NAME": "소득분배지표",
        "KEYSTAT_NAME": "5분위배율",
        "DATA_VALUE": "5.72",
        "CYCLE": "2023",
        "UNIT_NAME": null
      },
      {
        "CLASS_NAME": "고용",
        "KEYSTAT_NAME": "실업률",
        "DATA_VALUE": "2.8",
        "CYCLE": "202505",
        "UNIT_NAME": "%"
      },
      {
        "CLASS_NAME": "고용",
        "KEYSTAT_NAME": "고용률",
        "DATA_VALUE": "63.8",
        "CYCLE": "202505",
        "UNIT_NAME": "%"
      },
      {
        "CLASS_NAME": "고용",
        "KEYSTAT_NAME": "경제활동인구",
        "DATA_VALUE": "30012",
        "CYCLE": "202505",
        "UNIT_NAME": "천명 "
      },
      {
        "CLASS_NAME": "고용",
        "KEYSTAT_NAME": "취업자수",
        "DATA_VALUE": "29160",
        "CYCLE": "202505",
        "UNIT_NAME": "천명 "
      },
      {
        "CLASS_NAME": "노동",
        "KEYSTAT_NAME": "시간당명목임금지수",
        "DATA_VALUE": "120.6",
        "CYCLE": "2024Q4",
        "UNIT_NAME": "2020=100"
      },
      {
        "CLASS_NAME": "노동",
        "KEYSTAT_NAME": "노동생산성지수",
        "DATA_VALUE": "114",
        "CYCLE": "2024Q4",
        "UNIT_NAME": "2020=100"
      },
      {
        "CLASS_NAME": "노동",
        "KEYSTAT_NAME": "단위노동비용지수",
        "DATA_VALUE": "107",
        "CYCLE": "2024Q4",
        "UNIT_NAME": "2020=100"
      },
      {
        "CLASS_NAME": "인구",
        "KEYSTAT_NAME": "추계인구",
        "DATA_VALUE": "51684.6",
        "CYCLE": "2025",
        "UNIT_NAME": "천명 "
      },
      {
        "CLASS_NAME": "인구",
        "KEYSTAT_NAME": "고령인구비율",
        "DATA_VALUE": "20.3",
        "CYCLE": "2025",
        "UNIT_NAME": "%"
      },
      {
        "CLASS_NAME": "인구",
        "KEYSTAT_NAME": "합계출산율",
        "DATA_VALUE": "0.75",
        "CYCLE": "2024",
        "UNIT_NAME": "명 "
      },
      {
        "CLASS_NAME": "국제수지",
        "KEYSTAT_NAME": "경상수지",
        "DATA_VALUE": "5701.7",
        "CYCLE": "202504",
        "UNIT_NAME": "백만달러"
      },
      {
        "CLASS_NAME": "국제수지",
        "KEYSTAT_NAME": "직접투자(자산)",
        "DATA_VALUE": "3002.9",
        "CYCLE": "202504",
        "UNIT_NAME": "백만달러"
      },
      {
        "CLASS_NAME": "국제수지",
        "KEYSTAT_NAME": "직접투자(부채)",
        "DATA_VALUE": "-319.1",
        "CYCLE": "202504",
        "UNIT_NAME": "백만달러"
      },
      {
        "CLASS_NAME": "국제수지",
        "KEYSTAT_NAME": "증권투자(자산)",
        "DATA_VALUE": "12327.2",
        "CYCLE": "202504",
        "UNIT_NAME": "백만달러"
      },
      {
        "CLASS_NAME": "국제수지",
        "KEYSTAT_NAME": "증권투자(부채)",
        "DATA_VALUE": "-2180.7",
        "CYCLE": "202504",
        "UNIT_NAME": "백만달러"
      },
      {
        "CLASS_NAME": "통관수출입",
        "KEYSTAT_NAME": "수출금액지수",
        "DATA_VALUE": "133.43",
        "CYCLE": "202505",
        "UNIT_NAME": "2020=100"
      },
      {
        "CLASS_NAME": "통관수출입",
        "KEYSTAT_NAME": "수입금액지수",
        "DATA_VALUE": "128.35",
        "CYCLE": "202505",
        "UNIT_NAME": "2020=100"
      },
      {
        "CLASS_NAME": "통관수출입",
        "KEYSTAT_NAME": "순상품교역조건지수",
        "DATA_VALUE": "94.5",
        "CYCLE": "202505",
        "UNIT_NAME": "2020=100"
      },
      {
        "CLASS_NAME": "통관수출입",
        "KEYSTAT_NAME": "소득교역조건지수",
        "DATA_VALUE": "114.8",
        "CYCLE": "202505",
        "UNIT_NAME": "2020=100"
      },
      {
        "CLASS_NAME": "대외채권/채무",
        "KEYSTAT_NAME": "외환보유액",
        "DATA_VALUE": "404595704",
        "CYCLE": "202505",
        "UNIT_NAME": "천달러"
      },
      {
        "CLASS_NAME": "대외채권/채무",
        "KEYSTAT_NAME": "대외채무",
        "DATA_VALUE": "683423.2",
        "CYCLE": "2025Q1",
        "UNIT_NAME": "백만달러"
      },
      {
        "CLASS_NAME": "대외채권/채무",
        "KEYSTAT_NAME": "대외채권",
        "DATA_VALUE": "1051314.2",
        "CYCLE": "2025Q1",
        "UNIT_NAME": "백만달러"
      },
      {
        "CLASS_NAME": "소비자/생산자 물가",
        "KEYSTAT_NAME": "소비자물가지수",
        "DATA_VALUE": "116.27",
        "CYCLE": "202505",
        "UNIT_NAME": "2020=100"
      },
      {
        "CLASS_NAME": "소비자/생산자 물가",
        "KEYSTAT_NAME": "농산물 및 석유류제외 소비자물가지수",
        "DATA_VALUE": "115.06",
        "CYCLE": "202505",
        "UNIT_NAME": "2020=100"
      },
      {
        "CLASS_NAME": "소비자/생산자 물가",
        "KEYSTAT_NAME": "생활물가지수",
        "DATA_VALUE": "119.2",
        "CYCLE": "202505",
        "UNIT_NAME": "2020=100"
      },
      {
        "CLASS_NAME": "소비자/생산자 물가",
        "KEYSTAT_NAME": "생산자물가지수",
        "DATA_VALUE": "119.66",
        "CYCLE": "202505",
        "UNIT_NAME": "2020=100"
      },
      {
        "CLASS_NAME": "수출입 물가",
        "KEYSTAT_NAME": "수출물가지수",
        "DATA_VALUE": "128.56",
        "CYCLE": "202505",
        "UNIT_NAME": "2020=100"
      },
      {
        "CLASS_NAME": "수출입 물가",
        "KEYSTAT_NAME": "수입물가지수",
        "DATA_VALUE": "134.63",
        "CYCLE": "202505",
        "UNIT_NAME": "2020=100"
      },
      {
        "CLASS_NAME": "부동산 가격",
        "KEYSTAT_NAME": "주택매매가격지수",
        "DATA_VALUE": "100",
        "CYCLE": "202505",
        "UNIT_NAME": "2021.6=100"
      },
      {
        "CLASS_NAME": "부동산 가격",
        "KEYSTAT_NAME": "주택전세가격지수",
        "DATA_VALUE": "100",
        "CYCLE": "202505",
        "UNIT_NAME": "2021.6=100"
      },
      {
        "CLASS_NAME": "부동산 가격",
        "KEYSTAT_NAME": "지가변동률(전기대비)",
        "DATA_VALUE": "0.18",
        "CYCLE": "202504",
        "UNIT_NAME": "%"
      },
      {
        "CLASS_NAME": "국제원자재가격",
        "KEYSTAT_NAME": "Duba유(현물)",
        "DATA_VALUE": "63.61",
        "CYCLE": "202505",
        "UNIT_NAME": "달러/배럴"
      },
      {
        "CLASS_NAME": "국제원자재가격",
        "KEYSTAT_NAME": "금",
        "DATA_VALUE": "3288.01",
        "CYCLE": "202505",
        "UNIT_NAME": "달러"
      }
    ]
  }
}